{"frames":[{"participantFrames":{"1":{"participantId":1,"position":{"x":561,"y":361},"currentGold":500,"totalGold":500,"level":1,"xp":0,"minionsKilled":0,"jungleMinionsKilled":0,"dominionScore":0,"teamScore":0},"2":{"participantId":2,"position":{"x":351,"y":293},"currentGold":500,"totalGold":500,"level":1,"xp":0,"minionsKilled":0,"jungleMinionsKilled":0,"dominionScore":0,"teamScore":0},"3":{"participantId":3,"position":{"x":561,"y":581},"currentGold":500,"totalGold":500,"level":1,"xp":0,"minionsKilled":0,"jungleMinionsKilled":0,"dominionScore":0,"teamScore":0},"4":{"participantId":4,"position":{"x":222,"y":471},"currentGold":500,"totalGold":500,"level":1,"xp":0,"minionsKilled":0,"jungleMinionsKilled":0,"dominionScore":0,"teamScore":0},"5":{"participantId":5,"position":{"x":311,"y":649},"currentGold":500,"totalGold":500,"level":1,"xp":0,"minionsKilled":0,"jungleMinionsKilled":0,"dominionScore":0,"teamScore":0},"6":{"participantId":6,"position":{"x":14486,"y":14291},"currentGold":500,"totalGold":500,"level":1,"xp":0,"minionsKilled":0,"jungleMinionsKilled":0,"dominionScore":0,"teamScore":0},"7":{"participantId":7,"position":{"x":14237,"y":14579},"currentGold":500,"totalGold":500,"level":1,"xp":0,"minionsKilled":0,"jungleMinionsKilled":0,"dominionScore":0,"teamScore":0},"8":{"participantId":8,"position":{"x":14277,"y":14223},"currentGold":500,"totalGold":500,"level":1,"xp":0,"minionsKilled":0,"jungleMinionsKilled":0,"dominionScore":0,"teamScore":0},"9":{"participantId":9,"position":{"x":14486,"y":14511},"currentGold":500,"totalGold":500,"level":1,"xp":0,"minionsKilled":0,"jungleMinionsKilled":0,"dominionScore":0,"teamScore":0},"10":{"participantId":10,"position":{"x":14148,"y":14401},"currentGold":500,"totalGold":500,"level":1,"xp":0,"minionsKilled":0,"jungleMinionsKilled":0,"dominionScore":0,"teamScore":0}},"events":[{"type":"WARD_PLACED","timestamp":0,"wardType":"UNDEFINED","creatorId":1}],"timestamp":189},{"participantFrames":{"1":{"participantId":1,"position":{"x":12751,"y":1758},"currentGold":0,"totalGold":500,"level":1,"xp":0,"minionsKilled":0,"jungleMinionsKilled":0,"dominionScore":0,"teamScore":0},"2":{"participantId":2,"position":{"x":12291,"y":1346},"currentGold":0,"totalGold":500,"level":1,"xp":0,"minionsKilled":0,"jungleMinionsKilled":0,"dominionScore":0,"teamScore":0},"3":{"participantId":3,"position":{"x":835,"y":10287},"currentGold":0,"totalGold":500,"level":1,"xp":0,"minionsKilled":0,"jungleMinionsKilled":0,"dominionScore":0,"teamScore":0},"4":{"participantId":4,"position":{"x":7144,"y":3539},"currentGold":0,"totalGold":500,"level":1,"xp":0,"minionsKilled":0,"jungleMinionsKilled":0,"dominionScore":0,"teamScore":0},"5":{"participantId":5,"position":{"x":6319,"y":6524},"currentGold":0,"totalGold":500,"level":1,"xp":0,"minionsKilled":0,"jungleMinionsKilled":0,"dominionScore":0,"teamScore":0},"6":{"participantId":6,"position":{"x":9418,"y":5570},"currentGold":0,"totalGold":500,"level":1,"xp":0,"minionsKilled":0,"jungleMinionsKilled":0,"dominionScore":0,"teamScore":0},"7":{"participantId":7,"position":{"x":13531,"y":2692},"currentGold":0,"totalGold":500,"level":1,"xp":0,"minionsKilled":0,"jungleMinionsKilled":0,"dominionScore":0,"teamScore":0},"8":{"participantId":8,"position":{"x":10048,"y":6446},"currentGold":0,"totalGold":500,"level":1,"xp":0,"minionsKilled":0,"jungleMinionsKilled":0,"dominionScore":0,"teamScore":0},"9":{"participantId":9,"position":{"x":11960,"y":3822},"currentGold":0,"totalGold":500,"level":1,"xp":0,"minionsKilled":0,"jungleMinionsKilled":0,"dominionScore":0,"teamScore":0},"10":{"participantId":10,"position":{"x":2950,"y":11328},"currentGold":0,"totalGold":500,"level":1,"xp":0,"minionsKilled":0,"jungleMinionsKilled":0,"dominionScore":0,"teamScore":0}},"events":[{"type":"ITEM_PURCHASED","timestamp":3624,"participantId":7,"itemId":3302},{"type":"ITEM_PURCHASED","timestamp":4020,"participantId":5,"itemId":1056},{"type":"ITEM_PURCHASED","timestamp":4218,"participantId":7,"itemId":2003},{"type":"ITEM_PURCHASED","timestamp":4383,"participantId":7,"itemId":2003},{"type":"ITEM_PURCHASED","timestamp":4449,"participantId":5,"itemId":2003},{"type":"ITEM_PURCHASED","timestamp":4548,"participantId":7,"itemId":2003},{"type":"ITEM_PURCHASED","timestamp":4779,"participantId":5,"itemId":2003},{"type":"ITEM_PURCHASED","timestamp":5307,"participantId":5,"itemId":3340},{"type":"ITEM_PURCHASED","timestamp":5670,"participantId":7,"itemId":3340},{"type":"ITEM_DESTROYED","timestamp":6264,"participantId":2,"itemId":3599},{"type":"ITEM_PURCHASED","timestamp":6726,"participantId":4,"itemId":1039},{"type":"ITEM_PURCHASED","timestamp":6891,"participantId":6,"itemId":3340},{"type":"ITEM_PURCHASED","timestamp":7089,"participantId":4,"itemId":2031},{"type":"ITEM_PURCHASED","timestamp":7320,"participantId":4,"itemId":3340},{"type":"ITEM_PURCHASED","timestamp":7584,"participantId":9,"itemId":1055},{"type":"ITEM_PURCHASED","timestamp":7782,"participantId":9,"itemId":2003},{"type":"ITEM_PURCHASED","timestamp":7947,"participantId":6,"itemId":2031},{"type":"ITEM_PURCHASED","timestamp":8013,"participantId":9,"itemId":3340},{"type":"ITEM_PURCHASED","timestamp":8277,"participantId":6,"itemId":1041},{"type":"SKILL_LEVEL_UP","timestamp":9267,"participantId":5,"skillSlot":2,"levelUpType":"NORMAL"},{"type":"ITEM_UNDO","timestamp":9696,"participantId":4,"afterId":3340,"beforeId":0},{"type":"ITEM_UNDO","timestamp":9696,"participantId":9,"afterId":3340,"beforeId":0},{"type":"ITEM_UNDO","timestamp":9828,"participantId":4,"afterId":0,"beforeId":2031},{"type":"ITEM_UNDO","timestamp":9894,"participantId":9,"afterId":0,"beforeId":2003},{"type":"ITEM_UNDO","timestamp":9960,"participantId":4,"afterId":0,"beforeId":1039},{"type":"ITEM_UNDO","timestamp":10026,"participantId":9,"afterId":0,"beforeId":1055},{"type":"ITEM_PURCHASED","timestamp":10785,"participantId":1,"itemId":3340},{"type":"ITEM_PURCHASED","timestamp":11148,"participantId":1,"itemId":2003},{"type":"ITEM_PURCHASED","timestamp":11511,"participantId":1,"itemId":2003},{"type":"ITEM_PURCHASED","timestamp":11676,"participantId":4,"itemId":1041},{"type":"ITEM_PURCHASED","timestamp":11775,"participantId":2,"itemId":1055},{"type":"ITEM_PURCHASED","timestamp":11808,"participantId":1,"itemId":2003},{"type":"ITEM_PURCHASED","timestamp":12006,"participantId":2,"itemId":2003},{"type":"ITEM_PURCHASED","timestamp":12204,"participantId":8,"itemId":1056},{"type":"ITEM_PURCHASED","timestamp":12237,"participantId":2,"itemId":3340},{"type":"ITEM_PURCHASED","timestamp":12435,"participantId":4,"itemId":2031},{"type":"ITEM_PURCHASED","timestamp":12501,"participantId":8,"itemId":2003},{"type":"ITEM_PURCHASED","timestamp":12666,"participantId":8,"itemId":2003},{"type":"ITEM_PURCHASED","timestamp":12666,"participantId":9,"itemId":1054},{"type":"ITEM_PURCHASED","timestamp":12864,"participantId":4,"itemId":3340},{"type":"ITEM_PURCHASED","timestamp":13029,"participantId":8,"itemId":3340},{"type":"ITEM_PURCHASED","timestamp":13095,"participantId":9,"itemId":2003},{"type":"ITEM_PURCHASED","timestamp":13326,"participantId":1,"itemId":3302},{"type":"ITEM_PURCHASED","timestamp":13821,"participantId":9,"itemId":3340},{"type":"ITEM_PURCHASED","timestamp":15174,"participantId":10,"itemId":1055},{"type":"ITEM_PURCHASED","timestamp":15504,"participantId":10,"itemId":2003},{"type":"ITEM_PURCHASED","timestamp":15801,"participantId":10,"itemId":3340},{"type":"ITEM_PURCHASED","timestamp":20322,"participantId":3,"itemId":1056},{"type":"ITEM_PURCHASED","timestamp":20685,"participantId":3,"itemId":2003},{"type":"ITEM_PURCHASED","timestamp":20850,"participantId":3,"itemId":2003},{"type":"ITEM_PURCHASED","timestamp":21246,"participantId":3,"itemId":3340},{"type":"SKILL_LEVEL_UP","timestamp":30058,"participantId":10,"skillSlot":1,"levelUpType":"NORMAL"},{"type":"SKILL_LEVEL_UP","timestamp":37087,"participantId":9,"skillSlot":1,"levelUpType":"NORMAL"},{"type":"SKILL_LEVEL_UP","timestamp":41542,"participantId":4,"skillSlot":3,"levelUpType":"NORMAL"},{"type":"WARD_PLACED","timestamp":42796,"wardType":"YELLOW_TRINKET","creatorId":2},{"type":"SKILL_LEVEL_UP","timestamp":43126,"participantId":6,"skillSlot":1,"levelUpType":"NORMAL"},{"type":"WARD_PLACED","timestamp":49199,"wardType":"YELLOW_TRINKET","creatorId":6},{"type":"WARD_PLACED","timestamp":49826,"wardType":"YELLOW_TRINKET","creatorId":10},{"type":"SKILL_LEVEL_UP","timestamp":59726,"participantId":2,"skillSlot":3,"levelUpType":"NORMAL"}],"timestamp":60221},{"participantFrames":{"1":{"participantId":1,"position":{"x":12129,"y":2196},"currentGold":45,"totalGold":545,"level":1,"xp":115,"minionsKilled":1,"jungleMinionsKilled":0,"dominionScore":0,"teamScore":0},"2":{"participantId":2,"position":{"x":12371,"y":2007},"currentGold":81,"totalGold":581,"level":1,"xp":115,"minionsKilled":3,"jungleMinionsKilled":0,"dominionScore":0,"teamScore":0},"3":{"participantId":3,"position":{"x":2258,"y":12747},"currentGold":98,"totalGold":598,"level":1,"xp":206,"minionsKilled":4,"jungleMinionsKilled":0,"dominionScore":0,"teamScore":0},"4":{"participantId":4,"position":{"x":3514,"y":6702},"currentGold":121,"totalGold":621,"level":2,"xp":280,"minionsKilled":0,"jungleMinionsKilled":4,"dominionScore":0,"teamScore":0},"5":{"participantId":5,"position":{"x":7661,"y":7631},"currentGold":112,"totalGold":612,"level":1,"xp":264,"minionsKilled":5,"jungleMinionsKilled":0,"dominionScore":0,"teamScore":0},"6":{"participantId":6,"position":{"x":11197,"y":8534},"currentGold":137,"totalGold":637,"level":2,"xp":320,"minionsKilled":0,"jungleMinionsKilled":5,"dominionScore":0,"teamScore":0},"7":{"participantId":7,"position":{"x":13187,"y":2380},"currentGold":45,"totalGold":545,"level":1,"xp":115,"minionsKilled":1,"jungleMinionsKilled":0,"dominionScore":0,"teamScore":0},"8":{"participantId":8,"position":{"x":8294,"y":8365},"currentGold":98,"totalGold":598,"level":1,"xp":206,"minionsKilled":4,"jungleMinionsKilled":0,"dominionScore":0,"teamScore":0},"9":{"participantId":9,"position":{"x":12900,"y":3128},"currentGold":81,"totalGold":581,"level":1,"xp":115,"minionsKilled":3,"jungleMinionsKilled":0,"dominionScore":0,"teamScore":0},"10":{"participantId":10,"position":{"x":2672,"y":12059},"currentGold":98,"totalGold":598,"level":1,"xp":206,"minionsKilled":4,"jungleMinionsKilled":0,"dominionScore":0,"teamScore":0}},"events":[{"type":"WARD_PLACED","timestamp":71906,"wardType":"YELLOW_TRINKET","creatorId":5},{"type":"SKILL_LEVEL_UP","timestamp":74844,"participantId":8,"skillSlot":1,"levelUpType":"NORMAL"},{"type":"SKILL_LEVEL_UP","timestamp":85503,"participantId":1,"skillSlot":3,"levelUpType":"NORMAL"},{"type":"SKILL_LEVEL_UP","timestamp":95523,"participantId":7,"skillSlot":2,"levelUpType":"NORMAL"},{"type":"SKILL_LEVEL_UP","timestamp":101529,"participantId":3,"skillSlot":3,"levelUpType":"NORMAL"},{"type":"SKILL_LEVEL_UP","timestamp":105227,"participantId":4,"skillSlot":2,"levelUpType":"NORMAL"},{"type":"SKILL_LEVEL_UP","timestamp":108626,"participantId":6,"skillSlot":2,"levelUpType":"NORMAL"},{"type":"WARD_PLACED","timestamp":109253,"wardType":"UNDEFINED","creatorId":6},{"type":"WARD_PLACED","timestamp":110047,"wardType":"UNDEFINED","creatorId":6},{"type":"WARD_PLACED","timestamp":110047,"wardType":"UNDEFINED","creatorId":10}],"timestamp":120247},{"participantFrames":{"1":{"participantId":1,"position":{"x":12483,"y":1502},"currentGold":210,"totalGold":710,"level":2,"xp":460,"minionsKilled":2,"jungleMinionsKilled":0,"dominionScore":0,"teamScore":0},"2":{"participantId":2,"position":{"x":11683,"y":1654},"currentGold":371,"totalGold":871,"level":2,"xp":460,"minionsKilled":12,"jungleMinionsKilled":0,"dominionScore":0,"teamScore":0},"3":{"participantId":3,"position":{"x":982,"y":10275},"currentGold":368,"totalGold":868,"level":2,"xp":588,"minionsKilled":12,"jungleMinionsKilled":0,"dominionScore":0,"teamScore":0},"4":{"participantId":4,"position":{"x":1551,"y":11333},"currentGold":514,"totalGold":1014,"level":3,"xp":799,"minionsKilled":1,"jungleMinionsKilled":16,"dominionScore":0,"teamScore":0},"5":{"participantId":5,"position":{"x":7713,"y":7765},"currentGold":484,"totalGold":984,"level":3,"xp":886,"minionsKilled":17,"jungleMinionsKilled":0,"dominionScore":0,"teamScore":0},"6":{"participantId":6,"position":{"x":1798,"y":11564},"currentGold":443,"totalGold":943,"level":3,"xp":797,"minionsKilled":0,"jungleMinionsKilled":12,"dominionScore":0,"teamScore":0},"7":{"participantId":7,"position":{"x":13122,"y":2232},"currentGold":257,"totalGold":757,"level":2,"xp":559,"minionsKilled":3,"jungleMinionsKilled":0,"dominionScore":0,"teamScore":0},"8":{"participantId":8,"position":{"x":8797,"y":8291},"currentGold":376,"totalGold":876,"level":3,"xp":886,"minionsKilled":11,"jungleMinionsKilled":0,"dominionScore":0,"teamScore":0},"9":{"participantId":9,"position":{"x":12645,"y":2715},"currentGold":487,"totalGold":987,"level":2,"xp":559,"minionsKilled":17,"jungleMinionsKilled":0,"dominionScore":0,"teamScore":0},"10":{"participantId":10,"position":{"x":1971,"y":11927},"currentGold":425,"totalGold":925,"level":3,"xp":675,"minionsKilled":15,"jungleMinionsKilled":0,"dominionScore":0,"teamScore":0}},"events":[{"type":"SKILL_LEVEL_UP","timestamp":121402,"participantId":5,"skillSlot":1,"levelUpType":"NORMAL"},{"type":"SKILL_LEVEL_UP","timestamp":132857,"participantId":8,"skillSlot":3,"levelUpType":"NORMAL"},{"type":"WARD_KILL","timestamp":133781,"wardType":"UNDEFINED","killerId":4},{"type":"SKILL_LEVEL_UP","timestamp":133847,"participantId":10,"skillSlot":2,"levelUpType":"NORMAL"},{"type":"WARD_PLACED","timestamp":135893,"wardType":"UNDEFINED","creatorId":6},{"type":"WARD_PLACED","timestamp":136025,"wardType":"YELLOW_TRINKET","creatorId":4},{"type":"SKILL_LEVEL_UP","timestamp":139358,"participantId":1,"skillSlot":1,"levelUpType":"NORMAL"},{"type":"WARD_PLACED","timestamp":139556,"wardType":"YELLOW_TRINKET","creatorId":7},{"type":"SKILL_LEVEL_UP","timestamp":140843,"participantId":2,"skillSlot":1,"levelUpType":"NORMAL"},{"type":"SKILL_LEVEL_UP","timestamp":143946,"participantId":3,"skillSlot":1,"levelUpType":"NORMAL"},{"type":"SKILL_LEVEL_UP","timestamp":151635,"participantId":6,"skillSlot":3,"levelUpType":"NORMAL"},{"type":"SKILL_LEVEL_UP","timestamp":154671,"participantId":4,"skillSlot":1,"levelUpType":"NORMAL"},{"type":"SKILL_LEVEL_UP","timestamp":156948,"participantId":9,"skillSlot":2,"levelUpType":"NORMAL"},{"type":"SKILL_LEVEL_UP","timestamp":160583,"participantId":5,"skillSlot":3,"levelUpType":"NORMAL"},{"type":"SKILL_LEVEL_UP","timestamp":160880,"participantId":7,"skillSlot":1,"levelUpType":"NORMAL"},{"type":"WARD_PLACED","timestamp":161210,"wardType":"UNDEFINED","creatorId":6},{"type":"SKILL_LEVEL_UP","timestamp":170849,"participantId":8,"skillSlot":1,"levelUpType":"NORMAL"},{"type":"SKILL_LEVEL_UP","timestamp":175370,"participantId":10,"skillSlot":3,"levelUpType":"NORMAL"},{"type":"ITEM_DESTROYED","timestamp":176063,"participantId":10,"itemId":2003},{"type":"WARD_PLACED","timestamp":177812,"wardType":"YELLOW_TRINKET","creatorId":1}],"timestamp":180258},{"participantFrames":{"1":{"participantId":1,"position":{"x":11609,"y":1473},"currentGold":449,"totalGold":949,"level":3,"xp":770,"minionsKilled":4,"jungleMinionsKilled":0,"dominionScore":0,"teamScore":0},"2":{"participantId":2,"position":{"x":11747,"y":1581},"currentGold":719,"totalGold":1219,"level":3,"xp":770,"minionsKilled":23,"jungleMinionsKilled":0,"dominionScore":0,"teamScore":0},"3":{"participantId":3,"position":{"x":1422,"y":11179},"currentGold":210,"totalGold":1085,"level":3,"xp":853,"minionsKilled":17,"jungleMinionsKilled":0,"dominionScore":0,"teamScore":0},"4":{"participantId":4,"position":{"x":8636,"y":2446},"currentGold":212,"totalGold":1137,"level":3,"xp":799,"minionsKilled":1,"jungleMinionsKilled":16,"dominionScore":0,"teamScore":0},"5":{"participantId":5,"position":{"x":9171,"y":7484},"currentGold":1096,"totalGold":1596,"level":4,"xp":1631,"minionsKilled":27,"jungleMinionsKilled":0,"dominionScore":0,"teamScore":0},"6":{"participantId":6,"position":{"x":8691,"y":6727},"currentGold":1052,"totalGold":1552,"level":3,"xp":1137,"minionsKilled":0,"jungleMinionsKilled":16,"dominionScore":0,"teamScore":0},"7":{"participantId":7,"position":{"x":12570,"y":2284},"currentGold":442,"totalGold":942,"level":3,"xp":885,"minionsKilled":4,"jungleMinionsKilled":0,"dominionScore":0,"teamScore":0},"8":{"participantId":8,"position":{"x":8864,"y":7863},"currentGold":573,"totalGold":1073,"level":4,"xp":1396,"minionsKilled":15,"jungleMinionsKilled":0,"dominionScore":0,"teamScore":0},"9":{"participantId":9,"position":{"x":12705,"y":2022},"currentGold":799,"totalGold":1299,"level":3,"xp":885,"minionsKilled":27,"jungleMinionsKilled":0,"dominionScore":0,"teamScore":0},"10":{"participantId":10,"position":{"x":2546,"y":11605},"currentGold":785,"totalGold":1285,"level":4,"xp":1386,"minionsKilled":28,"jungleMinionsKilled":0,"dominionScore":0,"teamScore":0}},"events":[{"type":"WARD_PLACED","timestamp":182337,"wardType":"UNDEFINED","creatorId":1},{"type":"ITEM_DESTROYED","timestamp":185967,"participantId":5,"itemId":2010},{"type":"ITEM_PURCHASED","timestamp":186726,"participantId":3,"itemId":1001},{"type":"ITEM_PURCHASED","timestamp":189273,"participantId":3,"itemId":2055},{"type":"WARD_PLACED","timestamp":190297,"wardType":"UNDEFINED","creatorId":6},{"type":"WARD_PLACED","timestamp":194884,"wardType":"CONTROL_WARD","creatorId":3},{"type":"ITEM_DESTROYED","timestamp":194884,"participantId":3,"itemId":2055},{"type":"WARD_PLACED","timestamp":195115,"wardType":"YELLOW_TRINKET","creatorId":4},{"type":"SKILL_LEVEL_UP","timestamp":196468,"participantId":5,"skillSlot":2,"levelUpType":"NORMAL"},{"type":"CHAMPION_KILL","timestamp":199042,"position":{"x":1956,"y":9799},"killerId":6,"victimId":4,"assistingParticipantIds":[]},{"type":"WARD_PLACED","timestamp":200736,"wardType":"YELLOW_TRINKET","creatorId":6},{"type":"SKILL_LEVEL_UP","timestamp":201665,"participantId":7,"skillSlot":3,"levelUpType":"NORMAL"},{"type":"SKILL_LEVEL_UP","timestamp":202226,"participantId":9,"skillSlot":3,"levelUpType":"NORMAL"},{"type":"WARD_PLACED","timestamp":204404,"wardType":"UNDEFINED","creatorId":6},{"type":"SKILL_LEVEL_UP","timestamp":205229,"participantId":3,"skillSlot":2,"levelUpType":"NORMAL"},{"type":"SKILL_LEVEL_UP","timestamp":206780,"participantId":8,"skillSlot":2,"levelUpType":"NORMAL"},{"type":"ITEM_DESTROYED","timestamp":210047,"participantId":8,"itemId":2003},{"type":"SKILL_LEVEL_UP","timestamp":211928,"participantId":2,"skillSlot":2,"levelUpType":"NORMAL"},{"type":"SKILL_LEVEL_UP","timestamp":213051,"participantId":1,"skillSlot":2,"levelUpType":"NORMAL"},{"type":"ITEM_PURCHASED","timestamp":214800,"participantId":4,"itemId":1039},{"type":"ITEM_PURCHASED","timestamp":216088,"participantId":4,"itemId":2055},{"type":"WARD_PLACED","timestamp":218339,"wardType":"UNDEFINED","creatorId":6},{"type":"WARD_PLACED","timestamp":219362,"wardType":"YELLOW_TRINKET","creatorId":9},{"type":"WARD_PLACED","timestamp":219593,"wardType":"UNDEFINED","creatorId":1},{"type":"ITEM_DESTROYED","timestamp":222200,"participantId":8,"itemId":2003},{"type":"SKILL_LEVEL_UP","timestamp":225211,"participantId":10,"skillSlot":1,"levelUpType":"NORMAL"},{"type":"ITEM_DESTROYED","timestamp":225772,"participantId":1,"itemId":2003},{"type":"ITEM_DESTROYED","timestamp":231250,"participantId":5,"itemId":2003},{"type":"ITEM_DESTROYED","timestamp":231349,"participantId":7,"itemId":2003},{"type":"CHAMPION_KILL","timestamp":238380,"position":{"x":8864,"y":7863},"killerId":5,"victimId":8,"assistingParticipantIds":[]}],"timestamp":240261},{"participantFrames":{"1":{"participantId":1,"position":{"x":10952,"y":1312},"currentGold":662,"totalGold":1162,"level":4,"xp":1272,"minionsKilled":6,"jungleMinionsKilled":0,"dominionScore":0,"teamScore":0},"2":{"participantId":2,"position":{"x":11128,"y":1124},"currentGold":1136,"totalGold":1636,"level":4,"xp":1272,"minionsKilled":37,"jungleMinionsKilled":0,"dominionScore":0,"teamScore":0},"3":{"participantId":3,"position":{"x":997,"y":11111},"currentGold":246,"totalGold":1471,"level":4,"xp":1534,"minionsKilled":30,"jungleMinionsKilled":0,"dominionScore":0,"teamScore":0},"4":{"participantId":4,"position":{"x":3932,"y":6200},"currentGold":606,"totalGold":1531,"level":4,"xp":1408,"minionsKilled":1,"jungleMinionsKilled":24,"dominionScore":0,"teamScore":0},"5":{"participantId":5,"position":{"x":7441,"y":7507},"currentGold":148,"totalGold":1753,"level":5,"xp":1720,"minionsKilled":29,"jungleMinionsKilled":0,"dominionScore":0,"teamScore":0},"6":{"participantId":6,"position":{"x":1222,"y":12177},"currentGold":1908,"totalGold":2408,"level":5,"xp":1844,"minionsKilled":6,"jungleMinionsKilled":16,"dominionScore":0,"teamScore":0},"7":{"participantId":7,"position":{"x":11646,"y":3088},"currentGold":636,"totalGold":1136,"level":4,"xp":1329,"minionsKilled":5,"jungleMinionsKilled":0,"dominionScore":0,"teamScore":0},"8":{"participantId":8,"position":{"x":8092,"y":8399},"currentGold":111,"totalGold":1346,"level":4,"xp":1562,"minionsKilled":15,"jungleMinionsKilled":0,"dominionScore":0,"teamScore":0},"9":{"participantId":9,"position":{"x":11731,"y":2807},"currentGold":1225,"totalGold":1725,"level":4,"xp":1329,"minionsKilled":42,"jungleMinionsKilled":0,"dominionScore":0,"teamScore":0},"10":{"participantId":10,"position":{"x":2240,"y":11872},"currentGold":326,"totalGold":1676,"level":5,"xp":1723,"minionsKilled":34,"jungleMinionsKilled":0,"dominionScore":0,"teamScore":0}},"events":[{"type":"WARD_PLACED","timestamp":241053,"wardType":"YELLOW_TRINKET","creatorId":10},{"type":"WARD_PLACED","timestamp":242307,"wardType":"YELLOW_TRINKET","creatorId":5},{"type":"CHAMPION_KILL","timestamp":242967,"position":{"x":9300,"y":7153},"killerId":6,"victimId":5,"assistingParticipantIds":[8]},{"type":"SKILL_LEVEL_UP","timestamp":243924,"participantId":6,"skillSlot":1,"levelUpType":"NORMAL"},{"type":"WARD_PLACED","timestamp":246465,"wardType":"UNDEFINED","creatorId":10},{"type":"WARD_KILL","timestamp":246465,"wardType":"CONTROL_WARD","killerId":10},{"type":"SKILL_LEVEL_UP","timestamp":248381,"participantId":3,"skillSlot":3,"levelUpType":"NORMAL"},{"type":"ITEM_PURCHASED","timestamp":248777,"participantId":5,"itemId":3802},{"type":"ITEM_SOLD","timestamp":250597,"participantId":5,"itemId":2003},{"type":"ITEM_PURCHASED","timestamp":251257,"participantId":5,"itemId":2055},{"type":"ITEM_PURCHASED","timestamp":251719,"participantId":5,"itemId":2031},{"type":"WARD_PLACED","timestamp":253934,"wardType":"YELLOW_TRINKET","creatorId":1},{"type":"ITEM_DESTROYED","timestamp":254528,"participantId":1,"itemId":2003},{"type":"ITEM_PURCHASED","timestamp":254594,"participantId":8,"itemId":1001},{"type":"ITEM_PURCHASED","timestamp":256343,"participantId":8,"itemId":1052},{"type":"ITEM_DESTROYED","timestamp":257201,"participantId":3,"itemId":2003},{"type":"WARD_PLACED","timestamp":267993,"wardType":"UNDEFINED","creatorId":6},{"type":"SKILL_LEVEL_UP","timestamp":274823,"participantId":9,"skillSlot":2,"levelUpType":"NORMAL"},{"type":"ITEM_PURCHASED","timestamp":277143,"participantId":10,"itemId":1001},{"type":"ITEM_PURCHASED","timestamp":277605,"participantId":10,"itemId":1028},{"type":"WARD_PLACED","timestamp":278014,"wardType":"UNDEFINED","creatorId":1},{"type":"ITEM_PURCHASED","timestamp":278311,"participantId":10,"itemId":2031},{"type":"SKILL_LEVEL_UP","timestamp":284290,"participantId":4,"skillSlot":2,"levelUpType":"NORMAL"},{"type":"CHAMPION_KILL","timestamp":291125,"position":{"x":997,"y":11111},"killerId":6,"victimId":3,"assistingParticipantIds":[10]},{"type":"SKILL_LEVEL_UP","timestamp":291125,"participantId":2,"skillSlot":3,"levelUpType":"NORMAL"},{"type":"SKILL_LEVEL_UP","timestamp":293639,"participantId":6,"skillSlot":1,"levelUpType":"NORMAL"},{"type":"SKILL_LEVEL_UP","timestamp":294167,"participantId":5,"skillSlot":2,"levelUpType":"NORMAL"},{"type":"ITEM_PURCHASED","timestamp":296807,"participantId":3,"itemId":1082},{"type":"ITEM_DESTROYED","timestamp":300239,"participantId":0,"itemId":1501},{"type":"ITEM_DESTROYED","timestamp":300239,"participantId":0,"itemId":1501},{"type":"ITEM_DESTROYED","timestamp":300239,"participantId":0,"itemId":1501},{"type":"ITEM_DESTROYED","timestamp":300239,"participantId":0,"itemId":1501},{"type":"ITEM_DESTROYED","timestamp":300239,"participantId":0,"itemId":1501},{"type":"ITEM_DESTROYED","timestamp":300239,"participantId":0,"itemId":1501},{"type":"ITEM_DESTROYED","timestamp":300239,"participantId":0,"itemId":1501},{"type":"ITEM_DESTROYED","timestamp":300239,"participantId":0,"itemId":1501},{"type":"ITEM_DESTROYED","timestamp":300239,"participantId":0,"itemId":1501},{"type":"ITEM_DESTROYED","timestamp":300239,"participantId":0,"itemId":1501},{"type":"ITEM_DESTROYED","timestamp":300239,"participantId":0,"itemId":1501},{"type":"ITEM_DESTROYED","timestamp":300239,"participantId":0,"itemId":1501},{"type":"ITEM_DESTROYED","timestamp":300239,"participantId":0,"itemId":1501},{"type":"ITEM_DESTROYED","timestamp":300239,"participantId":0,"itemId":1501},{"type":"ITEM_DESTROYED","timestamp":300239,"participantId":0,"itemId":1501},{"type":"ITEM_DESTROYED","timestamp":300239,"participantId":0,"itemId":1501},{"type":"ITEM_DESTROYED","timestamp":300239,"participantId":0,"itemId":1501},{"type":"ITEM_DESTROYED","timestamp":300239,"participantId":0,"itemId":1501}],"timestamp":300272},{"participantFrames":{"1":{"participantId":1,"position":{"x":11971,"y":1991},"currentGold":837,"totalGold":1337,"level":4,"xp":1617,"minionsKilled":7,"jungleMinionsKilled":0,"dominionScore":0,"teamScore":0},"2":{"participantId":2,"position":{"x":11883,"y":1927},"currentGold":1484,"totalGold":1984,"level":4,"xp":1617,"minionsKilled":49,"jungleMinionsKilled":0,"dominionScore":0,"teamScore":0},"3":{"participantId":3,"position":{"x":2775,"y":12735},"currentGold":546,"totalGold":1771,"level":5,"xp":2038,"minionsKilled":38,"jungleMinionsKilled":0,"dominionScore":0,"teamScore":0},"4":{"participantId":4,"position":{"x":6208,"y":12289},"currentGold":931,"totalGold":1856,"level":5,"xp":1827,"minionsKilled":1,"jungleMinionsKilled":31,"dominionScore":0,"teamScore":0},"5":{"participantId":5,"position":{"x":7175,"y":7193},"currentGold":475,"totalGold":2080,"level":5,"xp":2342,"minionsKilled":40,"jungleMinionsKilled":0,"dominionScore":0,"teamScore":0},"6":{"participantId":6,"position":{"x":8277,"y":5577},"currentGold":302,"totalGold":2727,"level":5,"xp":2284,"minionsKilled":6,"jungleMinionsKilled":24,"dominionScore":0,"teamScore":0},"7":{"participantId":7,"position":{"x":13251,"y":2777},"currentGold":856,"totalGold":1356,"level":4,"xp":1716,"minionsKilled":7,"jungleMinionsKilled":0,"dominionScore":0,"teamScore":0},"8":{"participantId":8,"position":{"x":7767,"y":8088},"currentGold":466,"totalGold":1701,"level":5,"xp":2331,"minionsKilled":26,"jungleMinionsKilled":0,"dominionScore":0,"teamScore":0},"9":{"participantId":9,"position":{"x":13142,"y":2752},"currentGold":1584,"totalGold":2084,"level":4,"xp":1716,"minionsKilled":53,"jungleMinionsKilled":0,"dominionScore":0,"teamScore":0},"10":{"participantId":10,"position":{"x":5649,"y":13203},"currentGold":136,"totalGold":1911,"level":5,"xp":2065,"minionsKilled":40,"jungleMinionsKilled":0,"dominionScore":0,"teamScore":0}},"events":[{"type":"WARD_PLACED","timestamp":300479,"wardType":"UNDEFINED","creatorId":1},{"type":"SKILL_LEVEL_UP","timestamp":301370,"participantId":10,"skillSlot":1,"levelUpType":"NORMAL"},{"type":"WARD_PLACED","timestamp":302789,"wardType":"YELLOW_TRINKET","creatorId":9},{"type":"ITEM_PURCHASED","timestamp":304901,"participantId":6,"itemId":3715},{"type":"ITEM_DESTROYED","timestamp":304901,"participantId":6,"itemId":1041},{"type":"WARD_PLACED","timestamp":305528,"wardType":"YELLOW_TRINKET","creatorId":7},{"type":"ITEM_PURCHASED","timestamp":306716,"participantId":6,"itemId":3303},{"type":"ITEM_PURCHASED","timestamp":307972,"participantId":6,"itemId":1082},{"type":"ITEM_PURCHASED","timestamp":309381,"participantId":6,"itemId":1052},{"type":"ITEM_UNDO","timestamp":310536,"participantId":6,"afterId":0,"beforeId":1052},{"type":"ITEM_PURCHASED","timestamp":311790,"participantId":6,"itemId":3098},{"type":"ITEM_DESTROYED","timestamp":311790,"participantId":6,"itemId":3303},{"type":"WARD_PLACED","timestamp":311889,"wardType":"UNDEFINED","creatorId":10},{"type":"SKILL_LEVEL_UP","timestamp":312090,"participantId":1,"skillSlot":3,"levelUpType":"NORMAL"},{"type":"ITEM_PURCHASED","timestamp":312717,"participantId":6,"itemId":2055},{"type":"WARD_PLACED","timestamp":314004,"wardType":"CONTROL_WARD","creatorId":5},{"type":"ITEM_DESTROYED","timestamp":314004,"participantId":5,"itemId":2055},{"type":"SKILL_LEVEL_UP","timestamp":315820,"participantId":8,"skillSlot":1,"levelUpType":"NORMAL"},{"type":"SKILL_LEVEL_UP","timestamp":316117,"participantId":7,"skillSlot":1,"levelUpType":"NORMAL"},{"type":"WARD_PLACED","timestamp":319323,"wardType":"UNDEFINED","creatorId":1},{"type":"WARD_PLACED","timestamp":327111,"wardType":"CONTROL_WARD","creatorId":4},{"type":"ITEM_DESTROYED","timestamp":327111,"participantId":4,"itemId":2055},{"type":"WARD_PLACED","timestamp":327573,"wardType":"UNDEFINED","creatorId":6},{"type":"ITEM_PURCHASED","timestamp":335890,"participantId":10,"itemId":1036},{"type":"ITEM_PURCHASED","timestamp":338233,"participantId":10,"itemId":2055},{"type":"WARD_PLACED","timestamp":341236,"wardType":"UNDEFINED","creatorId":6},{"type":"SKILL_LEVEL_UP","timestamp":347021,"participantId":3,"skillSlot":3,"levelUpType":"NORMAL"},{"type":"SKILL_LEVEL_UP","timestamp":351311,"participantId":4,"skillSlot":2,"levelUpType":"NORMAL"},{"type":"WARD_PLACED","timestamp":358440,"wardType":"CONTROL_WARD","creatorId":6},{"type":"ITEM_DESTROYED","timestamp":358440,"participantId":6,"itemId":2055}],"timestamp":360295},{"participantFrames":{"1":{"participantId":1,"position":{"x":10649,"y":1462},"currentGold":1066,"totalGold":1566,"level":5,"xp":2023,"minionsKilled":9,"jungleMinionsKilled":0,"dominionScore":0,"teamScore":0},"2":{"participantId":2,"position":{"x":10147,"y":1068},"currentGold":1858,"totalGold":2358,"level":5,"xp":2023,"minionsKilled":61,"jungleMinionsKilled":0,"dominionScore":0,"teamScore":0},"3":{"participantId":3,"position":{"x":765,"y":4137},"currentGold":95,"totalGold":1970,"level":5,"xp":2303,"minionsKilled":43,"jungleMinionsKilled":0,"dominionScore":0,"teamScore":0},"4":{"participantId":4,"position":{"x":8205,"y":2360},"currentGold":58,"totalGold":2058,"level":5,"xp":1942,"minionsKilled":1,"jungleMinionsKilled":33,"dominionScore":0,"teamScore":0},"5":{"participantId":5,"position":{"x":6456,"y":6667},"currentGold":185,"totalGold":2240,"level":6,"xp":2548,"minionsKilled":42,"jungleMinionsKilled":0,"dominionScore":0,"teamScore":0},"6":{"participantId":6,"position":{"x":8003,"y":3490},"currentGold":806,"totalGold":3231,"level":6,"xp":2620,"minionsKilled":6,"jungleMinionsKilled":24,"dominionScore":0,"teamScore":0},"7":{"participantId":7,"position":{"x":8973,"y":3436},"currentGold":1041,"totalGold":1541,"level":5,"xp":2023,"minionsKilled":8,"jungleMinionsKilled":0,"dominionScore":0,"teamScore":0},"8":{"participantId":8,"position":{"x":13391,"y":12776},"currentGold":25,"totalGold":2210,"level":6,"xp":2991,"minionsKilled":38,"jungleMinionsKilled":0,"dominionScore":0,"teamScore":0},"9":{"participantId":9,"position":{"x":11664,"y":2906},"currentGold":1898,"totalGold":2398,"level":5,"xp":2111,"minionsKilled":63,"jungleMinionsKilled":0,"dominionScore":0,"teamScore":0},"10":{"participantId":10,"position":{"x":3106,"y":12898},"currentGold":478,"totalGold":2253,"level":6,"xp":2805,"minionsKilled":50,"jungleMinionsKilled":0,"dominionScore":0,"teamScore":0}},"events":[{"type":"SKILL_LEVEL_UP","timestamp":363067,"participantId":5,"skillSlot":4,"levelUpType":"NORMAL"},{"type":"SKILL_LEVEL_UP","timestamp":363265,"participantId":9,"skillSlot":2,"levelUpType":"NORMAL"},{"type":"SKILL_LEVEL_UP","timestamp":365047,"participantId":7,"skillSlot":1,"levelUpType":"NORMAL"},{"type":"ITEM_DESTROYED","timestamp":365410,"participantId":5,"itemId":2010},{"type":"WARD_PLACED","timestamp":367275,"wardType":"YELLOW_TRINKET","creatorId":8},{"type":"WARD_PLACED","timestamp":367868,"wardType":"UNDEFINED","creatorId":6},{"type":"WARD_PLACED","timestamp":370346,"wardType":"YELLOW_TRINKET","creatorId":6},{"type":"ITEM_DESTROYED","timestamp":370943,"participantId":3,"itemId":2003},{"type":"CHAMPION_KILL","timestamp":371372,"position":{"x":6147,"y":8370},"killerId":6,"victimId":5,"assistingParticipantIds":[8]},{"type":"SKILL_LEVEL_UP","timestamp":372428,"participantId":8,"skillSlot":4,"levelUpType":"NORMAL"},{"type":"SKILL_LEVEL_UP","timestamp":372461,"participantId":6,"skillSlot":4,"levelUpType":"NORMAL"},{"type":"WARD_PLACED","timestamp":374672,"wardType":"UNDEFINED","creatorId":6},{"type":"WARD_KILL","timestamp":374672,"wardType":"CONTROL_WARD","killerId":8},{"type":"ITEM_PURCHASED","timestamp":375003,"participantId":5,"itemId":1001},{"type":"ITEM_PURCHASED","timestamp":375631,"participantId":5,"itemId":2055},{"type":"ITEM_PURCHASED","timestamp":375961,"participantId":5,"itemId":2055},{"type":"WARD_PLACED","timestamp":378668,"wardType":"UNDEFINED","creatorId":1},{"type":"SKILL_LEVEL_UP","timestamp":383059,"participantId":10,"skillSlot":4,"levelUpType":"NORMAL"},{"type":"ITEM_DESTROYED","timestamp":384016,"participantId":7,"itemId":2003},{"type":"SKILL_LEVEL_UP","timestamp":384907,"participantId":2,"skillSlot":3,"levelUpType":"NORMAL"},{"type":"ITEM_DESTROYED","timestamp":385897,"participantId":2,"itemId":2003},{"type":"WARD_PLACED","timestamp":386623,"wardType":"UNDEFINED","creatorId":1},{"type":"WARD_PLACED","timestamp":387976,"wardType":"YELLOW_TRINKET","creatorId":3},{"type":"ITEM_PURCHASED","timestamp":390088,"participantId":4,"itemId":3706},{"type":"ITEM_DESTROYED","timestamp":390088,"participantId":4,"itemId":1039},{"type":"ITEM_DESTROYED","timestamp":390088,"participantId":4,"itemId":1041},{"type":"ITEM_PURCHASED","timestamp":391908,"participantId":4,"itemId":1028},{"type":"ITEM_PURCHASED","timestamp":392271,"participantId":4,"itemId":1001},{"type":"ITEM_PURCHASED","timestamp":393129,"participantId":4,"itemId":2055},{"type":"WARD_PLACED","timestamp":395835,"wardType":"YELLOW_TRINKET","creatorId":7},{"type":"WARD_PLACED","timestamp":396198,"wardType":"YELLOW_TRINKET","creatorId":3},{"type":"WARD_KILL","timestamp":397716,"wardType":"UNDEFINED","killerId":3},{"type":"SKILL_LEVEL_UP","timestamp":400103,"participantId":1,"skillSlot":3,"levelUpType":"NORMAL"},{"type":"WARD_PLACED","timestamp":401999,"wardType":"CONTROL_WARD","creatorId":10},{"type":"ITEM_DESTROYED","timestamp":401999,"participantId":10,"itemId":2055},{"type":"ITEM_PURCHASED","timestamp":408303,"participantId":3,"itemId":1029},{"type":"ITEM_PURCHASED","timestamp":410184,"participantId":3,"itemId":1029},{"type":"WARD_PLACED","timestamp":410316,"wardType":"UNDEFINED","creatorId":6},{"type":"ITEM_PURCHASED","timestamp":411801,"participantId":8,"itemId":3802},{"type":"ITEM_DESTROYED","timestamp":411801,"participantId":8,"itemId":1052},{"type":"ITEM_PURCHASED","timestamp":411966,"participantId":3,"itemId":2003},{"type":"ITEM_PURCHASED","timestamp":413055,"participantId":8,"itemId":1052},{"type":"ITEM_PURCHASED","timestamp":416345,"participantId":8,"itemId":2003}],"timestamp":420309},{"participantFrames":{"1":{"participantId":1,"position":{"x":10623,"y":1352},"currentGold":1266,"totalGold":1766,"level":5,"xp":2367,"minionsKilled":10,"jungleMinionsKilled":0,"dominionScore":0,"teamScore":0},"2":{"participantId":2,"position":{"x":10870,"y":1266},"currentGold":2157,"totalGold":2657,"level":6,"xp":2485,"minionsKilled":69,"jungleMinionsKilled":0,"dominionScore":0,"teamScore":0},"3":{"participantId":3,"position":{"x":1310,"y":10562},"currentGold":450,"totalGold":2325,"level":6,"xp":2866,"minionsKilled":54,"jungleMinionsKilled":0,"dominionScore":0,"teamScore":0},"4":{"participantId":4,"position":{"x":8742,"y":4195},"currentGold":230,"totalGold":2230,"level":5,"xp":2042,"minionsKilled":2,"jungleMinionsKilled":34,"dominionScore":0,"teamScore":0},"5":{"participantId":5,"position":{"x":8406,"y":6301},"currentGold":13,"totalGold":2503,"level":6,"xp":2941,"minionsKilled":51,"jungleMinionsKilled":0,"dominionScore":0,"teamScore":0},"6":{"participantId":6,"position":{"x":7565,"y":5024},"currentGold":1697,"totalGold":4122,"level":7,"xp":3352,"minionsKilled":6,"jungleMinionsKilled":29,"dominionScore":0,"teamScore":0},"7":{"participantId":7,"position":{"x":11720,"y":1991},"currentGold":1239,"totalGold":1739,"level":5,"xp":2217,"minionsKilled":10,"jungleMinionsKilled":0,"dominionScore":0,"teamScore":0},"8":{"participantId":8,"position":{"x":7243,"y":6542},"currentGold":500,"totalGold":2685,"level":7,"xp":3840,"minionsKilled":49,"jungleMinionsKilled":0,"dominionScore":0,"teamScore":0},"9":{"participantId":9,"position":{"x":12031,"y":1708},"currentGold":2221,"totalGold":2721,"level":6,"xp":2570,"minionsKilled":72,"jungleMinionsKilled":0,"dominionScore":0,"teamScore":0},"10":{"participantId":10,"position":{"x":2011,"y":11783},"currentGold":885,"totalGold":2660,"level":7,"xp":3515,"minionsKilled":64,"jungleMinionsKilled":0,"dominionScore":0,"teamScore":0}},"events":[{"type":"WARD_PLACED","timestamp":422420,"wardType":"UNDEFINED","creatorId":6},{"type":"WARD_PLACED","timestamp":433184,"wardType":"YELLOW_TRINKET","creatorId":1},{"type":"WARD_PLACED","timestamp":433250,"wardType":"YELLOW_TRINKET","creatorId":4},{"type":"WARD_PLACED","timestamp":436426,"wardType":"CONTROL_WARD","creatorId":5},{"type":"ITEM_DESTROYED","timestamp":436426,"participantId":5,"itemId":2055},{"type":"WARD_PLACED","timestamp":438165,"wardType":"YELLOW_TRINKET","creatorId":5},{"type":"WARD_PLACED","timestamp":438693,"wardType":"UNDEFINED","creatorId":1},{"type":"WARD_KILL","timestamp":440759,"wardType":"YELLOW_TRINKET","killerId":5},{"type":"WARD_PLACED","timestamp":444625,"wardType":"UNDEFINED","creatorId":6},{"type":"WARD_PLACED","timestamp":445064,"wardType":"CONTROL_WARD","creatorId":4},{"type":"ITEM_DESTROYED","timestamp":445064,"participantId":4,"itemId":2055},{"type":"WARD_KILL","timestamp":445625,"wardType":"UNDEFINED","killerId":5},{"type":"WARD_KILL","timestamp":448664,"wardType":"UNDEFINED","killerId":5},{"type":"SKILL_LEVEL_UP","timestamp":448796,"participantId":9,"skillSlot":4,"levelUpType":"NORMAL"},{"type":"SKILL_LEVEL_UP","timestamp":450051,"participantId":8,"skillSlot":1,"levelUpType":"NORMAL"},{"type":"WARD_KILL","timestamp":450183,"wardType":"UNDEFINED","killerId":5},{"type":"WARD_KILL","timestamp":450599,"wardType":"YELLOW_TRINKET","killerId":4},{"type":"SKILL_LEVEL_UP","timestamp":450731,"participantId":10,"skillSlot":1,"levelUpType":"NORMAL"},{"type":"WARD_PLACED","timestamp":452810,"wardType":"YELLOW_TRINKET","creatorId":10},{"type":"WARD_PLACED","timestamp":452942,"wardType":"UNDEFINED","creatorId":1},{"type":"SKILL_LEVEL_UP","timestamp":456770,"participantId":3,"skillSlot":4,"levelUpType":"NORMAL"},{"type":"WARD_PLACED","timestamp":457999,"wardType":"YELLOW_TRINKET","creatorId":9},{"type":"CHAMPION_KILL","timestamp":463466,"position":{"x":8406,"y":6301},"killerId":6,"victimId":5,"assistingParticipantIds":[8]},{"type":"SKILL_LEVEL_UP","timestamp":464522,"participantId":6,"skillSlot":1,"levelUpType":"NORMAL"},{"type":"SKILL_LEVEL_UP","timestamp":468910,"participantId":2,"skillSlot":4,"levelUpType":"NORMAL"},{"type":"WARD_PLACED","timestamp":469702,"wardType":"UNDEFINED","creatorId":1},{"type":"WARD_PLACED","timestamp":471654,"wardType":"UNDEFINED","creatorId":6},{"type":"ITEM_DESTROYED","timestamp":472083,"participantId":3,"itemId":2003},{"type":"CHAMPION_KILL","timestamp":473678,"position":{"x":8742,"y":4195},"killerId":6,"victimId":4,"assistingParticipantIds":[]},{"type":"ITEM_PURCHASED","timestamp":475526,"participantId":5,"itemId":1052}],"timestamp":480330},{"participantFrames":{"1":{"participantId":1,"position":{"x":12010,"y":3638},"currentGold":134,"totalGold":1934,"level":6,"xp":2523,"minionsKilled":12,"jungleMinionsKilled":0,"dominionScore":0,"teamScore":0},"2":{"participantId":2,"position":{"x":12436,"y":1346},"currentGold":2519,"totalGold":3019,"level":6,"xp":3053,"minionsKilled":82,"jungleMinionsKilled":0,"dominionScore":0,"teamScore":0},"3":{"participantId":3,"position":{"x":882,"y":11283},"currentGold":57,"totalGold":2582,"level":7,"xp":3278,"minionsKilled":61,"jungleMinionsKilled":0,"dominionScore":0,"teamScore":0},"4":{"participantId":4,"position":{"x":2336,"y":8404},"currentGold":453,"totalGold":2453,"level":5,"xp":2322,"minionsKilled":2,"jungleMinionsKilled":38,"dominionScore":0,"teamScore":0},"5":{"participantId":5,"position":{"x":6947,"y":8863},"currentGold":296,"totalGold":2786,"level":7,"xp":3328,"minionsKilled":58,"jungleMinionsKilled":0,"dominionScore":0,"teamScore":0},"6":{"participantId":6,"position":{"x":2768,"y":11392},"currentGold":2437,"totalGold":4862,"level":8,"xp":4212,"minionsKilled":6,"jungleMinionsKilled":37,"dominionScore":0,"teamScore":0},"7":{"participantId":7,"position":{"x":8217,"y":8532},"currentGold":-173,"totalGold":1882,"level":6,"xp":2428,"minionsKilled":10,"jungleMinionsKilled":0,"dominionScore":0,"teamScore":0},"8":{"participantId":8,"position":{"x":6214,"y":8924},"currentGold":838,"totalGold":3023,"level":8,"xp":4462,"minionsKilled":59,"jungleMinionsKilled":0,"dominionScore":0,"teamScore":0},"9":{"participantId":9,"position":{"x":13814,"y":7607},"currentGold":267,"totalGold":2992,"level":6,"xp":2782,"minionsKilled":80,"jungleMinionsKilled":0,"dominionScore":0,"teamScore":0},"10":{"participantId":10,"position":{"x":2105,"y":12296},"currentGold":1315,"totalGold":3090,"level":8,"xp":4231,"minionsKilled":71,"jungleMinionsKilled":0,"dominionScore":0,"teamScore":0}},"events":[{"type":"SKILL_LEVEL_UP","timestamp":488543,"participantId":1,"skillSlot":4,"levelUpType":"NORMAL"},{"type":"SKILL_LEVEL_UP","timestamp":491084,"participantId":8,"skillSlot":3,"levelUpType":"NORMAL"},{"type":"WARD_PLACED","timestamp":492239,"wardType":"YELLOW_TRINKET","creatorId":2},{"type":"ITEM_PURCHASED","timestamp":500755,"participantId":1,"itemId":3097},{"type":"ITEM_DESTROYED","timestamp":500755,"participantId":1,"itemId":3302},{"type":"ITEM_PURCHASED","timestamp":503076,"participantId":1,"itemId":2049},{"type":"ITEM_PURCHASED","timestamp":503736,"participantId":1,"itemId":3341},{"type":"ITEM_DESTROYED","timestamp":503736,"participantId":1,"itemId":3340},{"type":"WARD_PLACED","timestamp":504495,"wardType":"YELLOW_TRINKET","creatorId":2},{"type":"SKILL_LEVEL_UP","timestamp":505716,"participantId":7,"skillSlot":4,"levelUpType":"NORMAL"},{"type":"SKILL_LEVEL_UP","timestamp":509825,"participantId":3,"skillSlot":3,"levelUpType":"NORMAL"},{"type":"ITEM_PURCHASED","timestamp":511212,"participantId":7,"itemId":3117},{"type":"ITEM_PURCHASED","timestamp":512906,"participantId":7,"itemId":1028},{"type":"ITEM_PURCHASED","timestamp":513700,"participantId":7,"itemId":2055},{"type":"ITEM_SOLD","timestamp":514921,"participantId":7,"itemId":2003},{"type":"ITEM_PURCHASED","timestamp":515880,"participantId":7,"itemId":2031},{"type":"ITEM_PURCHASED","timestamp":516856,"participantId":9,"itemId":1043},{"type":"WARD_PLACED","timestamp":518770,"wardType":"YELLOW_TRINKET","creatorId":6},{"type":"ITEM_PURCHASED","timestamp":519100,"participantId":9,"itemId":1001},{"type":"ITEM_PURCHASED","timestamp":520552,"participantId":9,"itemId":1037},{"type":"ITEM_PURCHASED","timestamp":522968,"participantId":9,"itemId":2003},{"type":"WARD_PLACED","timestamp":524953,"wardType":"UNDEFINED","creatorId":6},{"type":"SKILL_LEVEL_UP","timestamp":526207,"participantId":5,"skillSlot":2,"levelUpType":"NORMAL"},{"type":"WARD_PLACED","timestamp":528913,"wardType":"YELLOW_TRINKET","creatorId":10},{"type":"CHAMPION_KILL","timestamp":530827,"position":{"x":882,"y":11283},"killerId":6,"victimId":3,"assistingParticipantIds":[10]},{"type":"WARD_PLACED","timestamp":532355,"wardType":"YELLOW_TRINKET","creatorId":8},{"type":"SKILL_LEVEL_UP","timestamp":533246,"participantId":10,"skillSlot":2,"levelUpType":"NORMAL"},{"type":"WARD_PLACED","timestamp":533939,"wardType":"YELLOW_TRINKET","creatorId":4},{"type":"WARD_PLACED","timestamp":534236,"wardType":"YELLOW_TRINKET","creatorId":5},{"type":"WARD_PLACED","timestamp":534236,"wardType":"UNDEFINED","creatorId":10},{"type":"ITEM_PURCHASED","timestamp":534513,"participantId":3,"itemId":3047},{"type":"ITEM_DESTROYED","timestamp":534513,"participantId":3,"itemId":1001},{"type":"ITEM_DESTROYED","timestamp":534513,"participantId":3,"itemId":1029},{"type":"ITEM_PURCHASED","timestamp":535767,"participantId":3,"itemId":2031},{"type":"SKILL_LEVEL_UP","timestamp":536993,"participantId":6,"skillSlot":3,"levelUpType":"NORMAL"}],"timestamp":540331},{"participantFrames":{"1":{"participantId":1,"position":{"x":12757,"y":1736},"currentGold":298,"totalGold":2098,"level":6,"xp":2624,"minionsKilled":13,"jungleMinionsKilled":0,"dominionScore":0,"teamScore":0},"2":{"participantId":2,"position":{"x":11795,"y":1453},"currentGold":182,"totalGold":3182,"level":6,"xp":3130,"minionsKilled":84,"jungleMinionsKilled":0,"dominionScore":0,"teamScore":0},"3":{"participantId":3,"position":{"x":1410,"y":11693},"currentGold":367,"totalGold":2892,"level":7,"xp":3838,"minionsKilled":71,"jungleMinionsKilled":0,"dominionScore":0,"teamScore":0},"4":{"participantId":4,"position":{"x":5644,"y":6226},"currentGold":732,"totalGold":2732,"level":6,"xp":3057,"minionsKilled":6,"jungleMinionsKilled":42,"dominionScore":0,"teamScore":0},"5":{"participantId":5,"position":{"x":5585,"y":6192},"currentGold":418,"totalGold":2908,"level":7,"xp":3347,"minionsKilled":58,"jungleMinionsKilled":0,"dominionScore":0,"teamScore":0},"6":{"participantId":6,"position":{"x":11415,"y":8207},"currentGold":47,"totalGold":4997,"level":8,"xp":4212,"minionsKilled":6,"jungleMinionsKilled":37,"dominionScore":0,"teamScore":0},"7":{"participantId":7,"position":{"x":5190,"y":6086},"currentGold":438,"totalGold":2493,"level":6,"xp":3131,"minionsKilled":11,"jungleMinionsKilled":0,"dominionScore":0,"teamScore":0},"8":{"participantId":8,"position":{"x":14278,"y":14282},"currentGold":348,"totalGold":3433,"level":8,"xp":5019,"minionsKilled":69,"jungleMinionsKilled":0,"dominionScore":0,"teamScore":0},"9":{"participantId":9,"position":{"x":13396,"y":2399},"currentGold":680,"totalGold":3405,"level":7,"xp":3492,"minionsKilled":94,"jungleMinionsKilled":0,"dominionScore":0,"teamScore":0},"10":{"participantId":10,"position":{"x":3869,"y":13225},"currentGold":308,"totalGold":3383,"level":8,"xp":4672,"minionsKilled":80,"jungleMinionsKilled":0,"dominionScore":0,"teamScore":0}},"events":[{"type":"WARD_PLACED","timestamp":546217,"wardType":"SIGHT_WARD","creatorId":1},{"type":"CHAMPION_KILL","timestamp":547750,"position":{"x":7194,"y":9886},"killerId":7,"victimId":5,"assistingParticipantIds":[8]},{"type":"ITEM_PURCHASED","timestamp":549498,"participantId":2,"itemId":3006},{"type":"ITEM_PURCHASED","timestamp":550389,"participantId":2,"itemId":1043},{"type":"ITEM_PURCHASED","timestamp":552868,"participantId":2,"itemId":1036},{"type":"ITEM_PURCHASED","timestamp":553792,"participantId":2,"itemId":2003},{"type":"WARD_PLACED","timestamp":554155,"wardType":"UNDEFINED","creatorId":6},{"type":"WARD_PLACED","timestamp":556630,"wardType":"SIGHT_WARD","creatorId":1},{"type":"SKILL_LEVEL_UP","timestamp":557884,"participantId":4,"skillSlot":4,"levelUpType":"NORMAL"},{"type":"WARD_PLACED","timestamp":559666,"wardType":"UNDEFINED","creatorId":1},{"type":"ITEM_PURCHASED","timestamp":566608,"participantId":10,"itemId":3044},{"type":"ITEM_DESTROYED","timestamp":566608,"participantId":10,"itemId":1028},{"type":"ITEM_DESTROYED","timestamp":566608,"participantId":10,"itemId":1036},{"type":"ITEM_PURCHASED","timestamp":568754,"participantId":10,"itemId":3067},{"type":"WARD_KILL","timestamp":571148,"wardType":"CONTROL_WARD","killerId":1},{"type":"WARD_PLACED","timestamp":572138,"wardType":"YELLOW_TRINKET","creatorId":7},{"type":"WARD_PLACED","timestamp":574944,"wardType":"YELLOW_TRINKET","creatorId":3},{"type":"ITEM_PURCHASED","timestamp":575373,"participantId":6,"itemId":1414},{"type":"ITEM_DESTROYED","timestamp":575373,"participantId":6,"itemId":3715},{"type":"ITEM_PURCHASED","timestamp":576429,"participantId":6,"itemId":1001},{"type":"SKILL_LEVEL_UP","timestamp":577457,"participantId":9,"skillSlot":2,"levelUpType":"NORMAL"},{"type":"ITEM_PURCHASED","timestamp":579650,"participantId":6,"itemId":3158},{"type":"ITEM_DESTROYED","timestamp":579650,"participantId":6,"itemId":1001},{"type":"WARD_PLACED","timestamp":591534,"wardType":"UNDEFINED","creatorId":2},{"type":"WARD_PLACED","timestamp":593844,"wardType":"UNDEFINED","creatorId":6},{"type":"ITEM_PURCHASED","timestamp":598083,"participantId":8,"itemId":3108},{"type":"ITEM_DESTROYED","timestamp":598083,"participantId":8,"itemId":1052},{"type":"CHAMPION_KILL","timestamp":598908,"position":{"x":5644,"y":6226},"killerId":7,"victimId":4,"assistingParticipantIds":[]},{"type":"ITEM_PURCHASED","timestamp":598908,"participantId":8,"itemId":1052},{"type":"WARD_PLACED","timestamp":599436,"wardType":"YELLOW_TRINKET","creatorId":9},{"type":"WARD_PLACED","timestamp":600096,"wardType":"UNDEFINED","creatorId":6}],"timestamp":600338},{"participantFrames":{"1":{"participantId":1,"position":{"x":4702,"y":877},"currentGold":69,"totalGold":2269,"level":6,"xp":2972,"minionsKilled":15,"jungleMinionsKilled":0,"dominionScore":0,"teamScore":0},"2":{"participantId":2,"position":{"x":11149,"y":1807},"currentGold":558,"totalGold":3558,"level":7,"xp":3537,"minionsKilled":96,"jungleMinionsKilled":0,"dominionScore":0,"teamScore":0},"3":{"participantId":3,"position":{"x":934,"y":10998},"currentGold":675,"totalGold":3200,"level":8,"xp":4401,"minionsKilled":79,"jungleMinionsKilled":0,"dominionScore":0,"teamScore":0},"4":{"participantId":4,"position":{"x":8677,"y":2371},"currentGold":359,"totalGold":2934,"level":7,"xp":3317,"minionsKilled":6,"jungleMinionsKilled":44,"dominionScore":0,"teamScore":0},"5":{"participantId":5,"position":{"x":6200,"y":7145},"currentGold":665,"totalGold":3155,"level":7,"xp":3649,"minionsKilled":64,"jungleMinionsKilled":0,"dominionScore":0,"teamScore":0},"6":{"participantId":6,"position":{"x":8148,"y":5181},"currentGold":672,"totalGold":5622,"level":9,"xp":5057,"minionsKilled":9,"jungleMinionsKilled":53,"dominionScore":0,"teamScore":0},"7":{"participantId":7,"position":{"x":10898,"y":3531},"currentGold":107,"totalGold":2637,"level":6,"xp":3131,"minionsKilled":11,"jungleMinionsKilled":0,"dominionScore":0,"teamScore":0},"8":{"participantId":8,"position":{"x":8077,"y":7070},"currentGold":719,"totalGold":3804,"level":9,"xp":5577,"minionsKilled":80,"jungleMinionsKilled":0,"dominionScore":0,"teamScore":0},"9":{"participantId":9,"position":{"x":10471,"y":3327},"currentGold":1079,"totalGold":3804,"level":8,"xp":4114,"minionsKilled":107,"jungleMinionsKilled":0,"dominionScore":0,"teamScore":0},"10":{"participantId":10,"position":{"x":1545,"y":11306},"currentGold":684,"totalGold":3759,"level":9,"xp":5324,"minionsKilled":92,"jungleMinionsKilled":0,"dominionScore":0,"teamScore":0}},"events":[{"type":"WARD_PLACED","timestamp":604184,"wardType":"UNDEFINED","creatorId":6},{"type":"SKILL_LEVEL_UP","timestamp":604811,"participantId":2,"skillSlot":3,"levelUpType":"NORMAL"},{"type":"WARD_PLACED","timestamp":606710,"wardType":"CONTROL_WARD","creatorId":7},{"type":"ITEM_DESTROYED","timestamp":606710,"participantId":7,"itemId":2055},{"type":"WARD_PLACED","timestamp":607189,"wardType":"CONTROL_WARD","creatorId":5},{"type":"ITEM_DESTROYED","timestamp":607189,"participantId":5,"itemId":2055},{"type":"WARD_PLACED","timestamp":609900,"wardType":"UNDEFINED","creatorId":1},{"type":"WARD_PLACED","timestamp":610197,"wardType":"UNDEFINED","creatorId":10},{"type":"ITEM_DESTROYED","timestamp":611796,"participantId":5,"itemId":2010},{"type":"WARD_KILL","timestamp":623475,"wardType":"CONTROL_WARD","killerId":5},{"type":"ITEM_PURCHASED","timestamp":624168,"participantId":4,"itemId":3751},{"type":"ITEM_DESTROYED","timestamp":624168,"participantId":4,"itemId":1028},{"type":"WARD_PLACED","timestamp":626577,"wardType":"UNDEFINED","creatorId":6},{"type":"ITEM_PURCHASED","timestamp":626775,"participantId":7,"itemId":2049},{"type":"ITEM_DESTROYED","timestamp":626775,"participantId":7,"itemId":1028},{"type":"ITEM_PURCHASED","timestamp":627930,"participantId":7,"itemId":3341},{"type":"ITEM_DESTROYED","timestamp":627930,"participantId":7,"itemId":3340},{"type":"ITEM_PURCHASED","timestamp":627996,"participantId":4,"itemId":2055},{"type":"ITEM_PURCHASED","timestamp":628929,"participantId":7,"itemId":2055},{"type":"SKILL_LEVEL_UP","timestamp":632691,"participantId":10,"skillSlot":1,"levelUpType":"NORMAL"},{"type":"ITEM_DESTROYED","timestamp":632757,"participantId":1,"itemId":2003},{"type":"SKILL_LEVEL_UP","timestamp":632955,"participantId":8,"skillSlot":1,"levelUpType":"NORMAL"},{"type":"WARD_PLACED","timestamp":635896,"wardType":"UNDEFINED","creatorId":1},{"type":"SKILL_LEVEL_UP","timestamp":638809,"participantId":3,"skillSlot":2,"levelUpType":"NORMAL"},{"type":"WARD_PLACED","timestamp":639304,"wardType":"UNDEFINED","creatorId":6},{"type":"WARD_KILL","timestamp":639304,"wardType":"CONTROL_WARD","killerId":6},{"type":"WARD_PLACED","timestamp":640801,"wardType":"YELLOW_TRINKET","creatorId":5},{"type":"WARD_PLACED","timestamp":642294,"wardType":"UNDEFINED","creatorId":2},{"type":"ITEM_PURCHASED","timestamp":647611,"participantId":1,"itemId":1028},{"type":"WARD_KILL","timestamp":653332,"wardType":"UNDEFINED","killerId":6},{"type":"WARD_PLACED","timestamp":653397,"wardType":"YELLOW_TRINKET","creatorId":8},{"type":"SKILL_LEVEL_UP","timestamp":653562,"participantId":9,"skillSlot":1,"levelUpType":"NORMAL"},{"type":"WARD_PLACED","timestamp":657736,"wardType":"CONTROL_WARD","creatorId":7},{"type":"ITEM_DESTROYED","timestamp":657736,"participantId":7,"itemId":2055},{"type":"SKILL_LEVEL_UP","timestamp":658305,"participantId":4,"skillSlot":2,"levelUpType":"NORMAL"},{"type":"WARD_KILL","timestamp":658571,"wardType":"SIGHT_WARD","killerId":8},{"type":"WARD_PLACED","timestamp":660089,"wardType":"UNDEFINED","creatorId":6},{"type":"WARD_KILL","timestamp":660089,"wardType":"YELLOW_TRINKET","killerId":6}],"timestamp":660371},{"participantFrames":{"1":{"participantId":1,"position":{"x":929,"y":709},"currentGold":334,"totalGold":2534,"level":7,"xp":3225,"minionsKilled":15,"jungleMinionsKilled":0,"dominionScore":0,"teamScore":0},"2":{"participantId":2,"position":{"x":2529,"y":669},"currentGold":21,"totalGold":4171,"level":7,"xp":3918,"minionsKilled":103,"jungleMinionsKilled":0,"dominionScore":0,"teamScore":0},"3":{"participantId":3,"position":{"x":1045,"y":6475},"currentGold":361,"totalGold":3486,"level":8,"xp":4695,"minionsKilled":86,"jungleMinionsKilled":0,"dominionScore":0,"teamScore":0},"4":{"participantId":4,"position":{"x":1383,"y":736},"currentGold":64,"totalGold":3239,"level":7,"xp":3648,"minionsKilled":7,"jungleMinionsKilled":46,"dominionScore":0,"teamScore":0},"5":{"participantId":5,"position":{"x":7715,"y":7914},"currentGold":1010,"totalGold":3500,"level":8,"xp":4271,"minionsKilled":74,"jungleMinionsKilled":0,"dominionScore":0,"teamScore":0},"6":{"participantId":6,"position":{"x":10549,"y":1314},"currentGold":1337,"totalGold":6287,"level":9,"xp":5536,"minionsKilled":10,"jungleMinionsKilled":57,"dominionScore":0,"teamScore":0},"7":{"participantId":7,"position":{"x":10893,"y":11141},"currentGold":-213,"totalGold":2942,"level":7,"xp":3367,"minionsKilled":11,"jungleMinionsKilled":0,"dominionScore":0,"teamScore":0},"8":{"participantId":8,"position":{"x":8645,"y":7836},"currentGold":1249,"totalGold":4334,"level":10,"xp":6304,"minionsKilled":90,"jungleMinionsKilled":0,"dominionScore":0,"teamScore":0},"9":{"participantId":9,"position":{"x":10960,"y":1190},"currentGold":1526,"totalGold":4251,"level":8,"xp":4736,"minionsKilled":116,"jungleMinionsKilled":0,"dominionScore":0,"teamScore":0},"10":{"participantId":10,"position":{"x":1323,"y":10772},"currentGold":1084,"totalGold":4159,"level":9,"xp":5945,"minionsKilled":105,"jungleMinionsKilled":0,"dominionScore":0,"teamScore":0}},"events":[{"type":"SKILL_LEVEL_UP","timestamp":661030,"participantId":6,"skillSlot":1,"levelUpType":"NORMAL"},{"type":"WARD_KILL","timestamp":662516,"wardType":"UNDEFINED","killerId":9},{"type":"WARD_PLACED","timestamp":662549,"wardType":"UNDEFINED","creatorId":6},{"type":"WARD_PLACED","timestamp":663672,"wardType":"YELLOW_TRINKET","creatorId":6},{"type":"ITEM_DESTROYED","timestamp":668652,"participantId":2,"itemId":2003},{"type":"WARD_PLACED","timestamp":672077,"wardType":"UNDEFINED","creatorId":1},{"type":"ITEM_DESTROYED","timestamp":677897,"participantId":9,"itemId":2003},{"type":"WARD_PLACED","timestamp":679771,"wardType":"SIGHT_WARD","creatorId":1},{"type":"WARD_PLACED","timestamp":681724,"wardType":"UNDEFINED","creatorId":1},{"type":"CHAMPION_KILL","timestamp":685450,"position":{"x":12882,"y":1792},"killerId":2,"victimId":7,"assistingParticipantIds":[1,4]},{"type":"CHAMPION_KILL","timestamp":688430,"position":{"x":12803,"y":1990},"killerId":6,"victimId":2,"assistingParticipantIds":[9,7]},{"type":"WARD_PLACED","timestamp":689886,"wardType":"UNDEFINED","creatorId":1},{"type":"WARD_PLACED","timestamp":691831,"wardType":"SIGHT_WARD","creatorId":1},{"type":"CHAMPION_KILL","timestamp":693556,"position":{"x":12727,"y":2186},"killerId":8,"victimId":4,"assistingParticipantIds":[9,7]},{"type":"SKILL_LEVEL_UP","timestamp":693721,"participantId":5,"skillSlot":1,"levelUpType":"NORMAL"},{"type":"WARD_PLACED","timestamp":698898,"wardType":"SIGHT_WARD","creatorId":1},{"type":"SKILL_LEVEL_UP","timestamp":700064,"participantId":7,"skillSlot":1,"levelUpType":"NORMAL"},{"type":"WARD_PLACED","timestamp":701463,"wardType":"UNDEFINED","creatorId":1},{"type":"SKILL_LEVEL_UP","timestamp":702694,"participantId":8,"skillSlot":3,"levelUpType":"NORMAL"},{"type":"ITEM_DESTROYED","timestamp":702727,"participantId":9,"itemId":2003},{"type":"ITEM_PURCHASED","timestamp":703255,"participantId":3,"itemId":3024},{"type":"ITEM_DESTROYED","timestamp":703255,"participantId":3,"itemId":1029},{"type":"ITEM_PURCHASED","timestamp":704807,"participantId":3,"itemId":1029},{"type":"ITEM_UNDO","timestamp":706887,"participantId":3,"afterId":0,"beforeId":1029},{"type":"ITEM_PURCHASED","timestamp":708852,"participantId":7,"itemId":3097},{"type":"ITEM_DESTROYED","timestamp":708852,"participantId":7,"itemId":3302},{"type":"ITEM_PURCHASED","timestamp":708951,"participantId":4,"itemId":1401},{"type":"ITEM_DESTROYED","timestamp":708951,"participantId":4,"itemId":3751},{"type":"ITEM_DESTROYED","timestamp":708951,"participantId":4,"itemId":3706},{"type":"ITEM_PURCHASED","timestamp":709908,"participantId":7,"itemId":2055},{"type":"ITEM_PURCHASED","timestamp":712524,"participantId":2,"itemId":3144},{"type":"ITEM_DESTROYED","timestamp":712524,"participantId":2,"itemId":1036}],"timestamp":720397},{"participantFrames":{"1":{"participantId":1,"position":{"x":7616,"y":7339},"currentGold":642,"totalGold":2842,"level":7,"xp":3417,"minionsKilled":20,"jungleMinionsKilled":0,"dominionScore":0,"teamScore":0},"2":{"participantId":2,"position":{"x":10906,"y":1602},"currentGold":448,"totalGold":4598,"level":8,"xp":4414,"minionsKilled":114,"jungleMinionsKilled":0,"dominionScore":0,"teamScore":0},"3":{"participantId":3,"position":{"x":6440,"y":9216},"currentGold":841,"totalGold":3966,"level":9,"xp":5313,"minionsKilled":100,"jungleMinionsKilled":0,"dominionScore":0,"teamScore":0},"4":{"participantId":4,"position":{"x":5836,"y":5191},"currentGold":548,"totalGold":3723,"level":8,"xp":4319,"minionsKilled":7,"jungleMinionsKilled":50,"dominionScore":0,"teamScore":0},"5":{"participantId":5,"position":{"x":7369,"y":7253},"currentGold":1714,"totalGold":4204,"level":9,"xp":5092,"minionsKilled":84,"jungleMinionsKilled":0,"dominionScore":0,"teamScore":0},"6":{"participantId":6,"position":{"x":10303,"y":3266},"currentGold":819,"totalGold":6819,"level":9,"xp":5632,"minionsKilled":13,"jungleMinionsKilled":57,"dominionScore":0,"teamScore":0},"7":{"participantId":7,"position":{"x":7528,"y":8916},"currentGold":146,"totalGold":3301,"level":7,"xp":3616,"minionsKilled":11,"jungleMinionsKilled":0,"dominionScore":0,"teamScore":0},"8":{"participantId":8,"position":{"x":8419,"y":8558},"currentGold":1768,"totalGold":4853,"level":10,"xp":6701,"minionsKilled":100,"jungleMinionsKilled":0,"dominionScore":0,"teamScore":0},"9":{"participantId":9,"position":{"x":7833,"y":10957},"currentGold":150,"totalGold":4750,"level":8,"xp":4950,"minionsKilled":118,"jungleMinionsKilled":0,"dominionScore":0,"teamScore":0},"10":{"participantId":10,"position":{"x":13388,"y":4925},"currentGold":291,"totalGold":5116,"level":10,"xp":6152,"minionsKilled":109,"jungleMinionsKilled":0,"dominionScore":0,"teamScore":0}},"events":[{"type":"BUILDING_KILL","timestamp":726934,"position":{"x":981,"y":10441},"killerId":0,"assistingParticipantIds":[],"teamId":100,"buildingType":"TOWER_BUILDING","laneType":"TOP_LANE","towerType":"OUTER_TURRET"},{"type":"ITEM_DESTROYED","timestamp":728820,"participantId":5,"itemId":2010},{"type":"BUILDING_KILL","timestamp":730990,"position":{"x":10504,"y":1029},"killerId":9,"assistingParticipantIds":[6],"teamId":100,"buildingType":"TOWER_BUILDING","laneType":"BOT_LANE","towerType":"OUTER_TURRET"},{"type":"SKILL_LEVEL_UP","timestamp":733202,"participantId":10,"skillSlot":2,"levelUpType":"NORMAL"},{"type":"WARD_PLACED","timestamp":735545,"wardType":"CONTROL_WARD","creatorId":7},{"type":"ITEM_DESTROYED","timestamp":735545,"participantId":7,"itemId":2055},{"type":"SKILL_LEVEL_UP","timestamp":735723,"participantId":1,"skillSlot":3,"levelUpType":"NORMAL"},{"type":"WARD_PLACED","timestamp":736812,"wardType":"YELLOW_TRINKET","creatorId":4},{"type":"WARD_PLACED","timestamp":737478,"wardType":"YELLOW_TRINKET","creatorId":2},{"type":"WARD_PLACED","timestamp":738270,"wardType":"UNDEFINED","creatorId":6},{"type":"WARD_PLACED","timestamp":740184,"wardType":"YELLOW_TRINKET","creatorId":10},{"type":"WARD_PLACED","timestamp":744038,"wardType":"UNDEFINED","creatorId":1},{"type":"SKILL_LEVEL_UP","timestamp":747547,"participantId":3,"skillSlot":3,"levelUpType":"NORMAL"},{"type":"ITEM_PURCHASED","timestamp":749263,"participantId":10,"itemId":3071},{"type":"ITEM_DESTROYED","timestamp":749263,"participantId":10,"itemId":3044},{"type":"ITEM_DESTROYED","timestamp":749263,"participantId":10,"itemId":3067},{"type":"ITEM_PURCHASED","timestamp":750121,"participantId":9,"itemId":3124},{"type":"ITEM_DESTROYED","timestamp":750121,"participantId":9,"itemId":1043},{"type":"ITEM_DESTROYED","timestamp":750121,"participantId":9,"itemId":1037},{"type":"WARD_PLACED","timestamp":751911,"wardType":"YELLOW_TRINKET","creatorId":3},{"type":"WARD_PLACED","timestamp":751977,"wardType":"UNDEFINED","creatorId":6},{"type":"ITEM_PURCHASED","timestamp":751977,"participantId":9,"itemId":2031},{"type":"ITEM_PURCHASED","timestamp":752214,"participantId":10,"itemId":3111},{"type":"ITEM_DESTROYED","timestamp":752214,"participantId":10,"itemId":1001},{"type":"CHAMPION_KILL","timestamp":752247,"position":{"x":10303,"y":3266},"killerId":5,"victimId":6,"assistingParticipantIds":[4]},{"type":"WARD_PLACED","timestamp":755087,"wardType":"SIGHT_WARD","creatorId":7},{"type":"WARD_PLACED","timestamp":759458,"wardType":"SIGHT_WARD","creatorId":1},{"type":"WARD_KILL","timestamp":762987,"wardType":"UNDEFINED","killerId":1},{"type":"WARD_PLACED","timestamp":768708,"wardType":"SIGHT_WARD","creatorId":1},{"type":"WARD_PLACED","timestamp":768840,"wardType":"SIGHT_WARD","creatorId":7},{"type":"WARD_KILL","timestamp":770028,"wardType":"UNDEFINED","killerId":1},{"type":"SKILL_LEVEL_UP","timestamp":770919,"participantId":2,"skillSlot":1,"levelUpType":"NORMAL"},{"type":"WARD_PLACED","timestamp":773790,"wardType":"SIGHT_WARD","creatorId":1},{"type":"SKILL_LEVEL_UP","timestamp":775671,"participantId":5,"skillSlot":2,"levelUpType":"NORMAL"},{"type":"WARD_PLACED","timestamp":776034,"wardType":"YELLOW_TRINKET","creatorId":9},{"type":"SKILL_LEVEL_UP","timestamp":776736,"participantId":4,"skillSlot":3,"levelUpType":"NORMAL"},{"type":"WARD_PLACED","timestamp":778716,"wardType":"YELLOW_TRINKET","creatorId":5},{"type":"ITEM_PURCHASED","timestamp":779475,"participantId":6,"itemId":3057}],"timestamp":780401},{"participantFrames":{"1":{"participantId":1,"position":{"x":4766,"y":7438},"currentGold":446,"totalGold":3046,"level":7,"xp":3650,"minionsKilled":21,"jungleMinionsKilled":0,"dominionScore":0,"teamScore":0},"2":{"participantId":2,"position":{"x":620,"y":1170},"currentGold":895,"totalGold":5045,"level":9,"xp":5166,"minionsKilled":114,"jungleMinionsKilled":0,"dominionScore":0,"teamScore":0},"3":{"participantId":3,"position":{"x":2709,"y":12585},"currentGold":95,"totalGold":4210,"level":9,"xp":5611,"minionsKilled":105,"jungleMinionsKilled":0,"dominionScore":0,"teamScore":0},"4":{"participantId":4,"position":{"x":3305,"y":6771},"currentGold":1008,"totalGold":4183,"level":9,"xp":5116,"minionsKilled":8,"jungleMinionsKilled":62,"dominionScore":0,"teamScore":0},"5":{"participantId":5,"position":{"x":7868,"y":7171},"currentGold":567,"totalGold":4622,"level":9,"xp":5766,"minionsKilled":98,"jungleMinionsKilled":0,"dominionScore":0,"teamScore":0},"6":{"participantId":6,"position":{"x":7688,"y":7965},"currentGold":1260,"totalGold":7260,"level":10,"xp":6306,"minionsKilled":13,"jungleMinionsKilled":69,"dominionScore":0,"teamScore":0},"7":{"participantId":7,"position":{"x":3186,"y":7111},"currentGold":561,"totalGold":3716,"level":8,"xp":4248,"minionsKilled":14,"jungleMinionsKilled":0,"dominionScore":0,"teamScore":0},"8":{"participantId":8,"position":{"x":11973,"y":11438},"currentGold":168,"totalGold":5243,"level":11,"xp":7323,"minionsKilled":112,"jungleMinionsKilled":0,"dominionScore":0,"teamScore":0},"9":{"participantId":9,"position":{"x":1629,"y":9084},"currentGold":1024,"totalGold":5624,"level":9,"xp":5790,"minionsKilled":130,"jungleMinionsKilled":8,"dominionScore":0,"teamScore":0},"10":{"participantId":10,"position":{"x":13689,"y":9008},"currentGold":363,"totalGold":5538,"level":10,"xp":6725,"minionsKilled":109,"jungleMinionsKilled":0,"dominionScore":0,"teamScore":0}},"events":[{"type":"WARD_PLACED","timestamp":780797,"wardType":"UNDEFINED","creatorId":1},{"type":"WARD_KILL","timestamp":784621,"wardType":"SIGHT_WARD","killerId":4},{"type":"SKILL_LEVEL_UP","timestamp":786648,"participantId":9,"skillSlot":2,"levelUpType":"NORMAL"},{"type":"CHAMPION_KILL","timestamp":794179,"position":{"x":12250,"y":1250},"killerId":2,"victimId":10,"assistingParticipantIds":[]},{"type":"CHAMPION_KILL","timestamp":794212,"position":{"x":12175,"y":1243},"killerId":10,"victimId":2,"assistingParticipantIds":[]},{"type":"WARD_PLACED","timestamp":796720,"wardType":"UNDEFINED","creatorId":6},{"type":"ITEM_PURCHASED","timestamp":800152,"participantId":5,"itemId":3165},{"type":"ITEM_DESTROYED","timestamp":800152,"participantId":5,"itemId":1052},{"type":"ITEM_DESTROYED","timestamp":800152,"participantId":5,"itemId":3802},{"type":"ITEM_PURCHASED","timestamp":801076,"participantId":5,"itemId":3363},{"type":"ITEM_DESTROYED","timestamp":801076,"participantId":5,"itemId":3340},{"type":"ITEM_PURCHASED","timestamp":813712,"participantId":1,"itemId":3067},{"type":"ITEM_DESTROYED","timestamp":813712,"participantId":1,"itemId":1028},{"type":"CHAMPION_KILL","timestamp":815146,"position":{"x":2709,"y":12585},"killerId":9,"victimId":3,"assistingParticipantIds":[7]},{"type":"ITEM_PURCHASED","timestamp":817134,"participantId":10,"itemId":1036},{"type":"SKILL_LEVEL_UP","timestamp":818091,"participantId":8,"skillSlot":4,"levelUpType":"NORMAL"},{"type":"ITEM_PURCHASED","timestamp":818757,"participantId":3,"itemId":3801},{"type":"SKILL_LEVEL_UP","timestamp":818856,"participantId":2,"skillSlot":3,"levelUpType":"NORMAL"},{"type":"SKILL_LEVEL_UP","timestamp":820078,"participantId":7,"skillSlot":2,"levelUpType":"NORMAL"},{"type":"ITEM_SOLD","timestamp":820144,"participantId":3,"itemId":2031},{"type":"ITEM_UNDO","timestamp":820705,"participantId":10,"afterId":0,"beforeId":1036},{"type":"ITEM_PURCHASED","timestamp":821203,"participantId":3,"itemId":1028},{"type":"ITEM_PURCHASED","timestamp":823446,"participantId":10,"itemId":1036},{"type":"ITEM_PURCHASED","timestamp":825266,"participantId":8,"itemId":3165},{"type":"ITEM_DESTROYED","timestamp":825266,"participantId":8,"itemId":3108},{"type":"ITEM_DESTROYED","timestamp":825266,"participantId":8,"itemId":1052},{"type":"ITEM_DESTROYED","timestamp":825266,"participantId":8,"itemId":3802},{"type":"WARD_PLACED","timestamp":826290,"wardType":"CONTROL_WARD","creatorId":4},{"type":"ITEM_DESTROYED","timestamp":826290,"participantId":4,"itemId":2055},{"type":"ITEM_PURCHASED","timestamp":827293,"participantId":8,"itemId":1058},{"type":"SKILL_LEVEL_UP","timestamp":827524,"participantId":6,"skillSlot":3,"levelUpType":"NORMAL"},{"type":"ITEM_PURCHASED","timestamp":829009,"participantId":8,"itemId":3364},{"type":"ITEM_DESTROYED","timestamp":829009,"participantId":8,"itemId":3340},{"type":"ITEM_PURCHASED","timestamp":830955,"participantId":8,"itemId":2055},{"type":"ITEM_PURCHASED","timestamp":830988,"participantId":2,"itemId":3363},{"type":"ITEM_DESTROYED","timestamp":830988,"participantId":2,"itemId":3340},{"type":"WARD_PLACED","timestamp":832176,"wardType":"UNDEFINED","creatorId":10},{"type":"WARD_PLACED","timestamp":834102,"wardType":"SIGHT_WARD","creatorId":7},{"type":"SKILL_LEVEL_UP","timestamp":839064,"participantId":4,"skillSlot":3,"levelUpType":"NORMAL"}],"timestamp":840422},{"participantFrames":{"1":{"participantId":1,"position":{"x":802,"y":512},"currentGold":259,"totalGold":3409,"level":7,"xp":4014,"minionsKilled":21,"jungleMinionsKilled":0,"dominionScore":0,"teamScore":0},"2":{"participantId":2,"position":{"x":1412,"y":10340},"currentGold":330,"totalGold":5380,"level":9,"xp":5809,"minionsKilled":122,"jungleMinionsKilled":0,"dominionScore":0,"teamScore":0},"3":{"participantId":3,"position":{"x":6144,"y":6527},"currentGold":590,"totalGold":4705,"level":9,"xp":5923,"minionsKilled":107,"jungleMinionsKilled":0,"dominionScore":0,"teamScore":0},"4":{"participantId":4,"position":{"x":3421,"y":2087},"currentGold":207,"totalGold":4382,"level":9,"xp":5347,"minionsKilled":9,"jungleMinionsKilled":62,"dominionScore":0,"teamScore":0},"5":{"participantId":5,"position":{"x":6997,"y":7184},"currentGold":1123,"totalGold":5178,"level":10,"xp":6267,"minionsKilled":103,"jungleMinionsKilled":0,"dominionScore":0,"teamScore":0},"6":{"participantId":6,"position":{"x":6088,"y":5629},"currentGold":1578,"totalGold":7578,"level":10,"xp":6564,"minionsKilled":15,"jungleMinionsKilled":69,"dominionScore":0,"teamScore":0},"7":{"participantId":7,"position":{"x":12073,"y":11444},"currentGold":-38,"totalGold":3892,"level":8,"xp":4371,"minionsKilled":14,"jungleMinionsKilled":0,"dominionScore":0,"teamScore":0},"8":{"participantId":8,"position":{"x":7616,"y":7758},"currentGold":746,"totalGold":5821,"level":11,"xp":7802,"minionsKilled":119,"jungleMinionsKilled":0,"dominionScore":0,"teamScore":0},"9":{"participantId":9,"position":{"x":14308,"y":14369},"currentGold":209,"totalGold":5909,"level":9,"xp":6059,"minionsKilled":134,"jungleMinionsKilled":8,"dominionScore":0,"teamScore":0},"10":{"participantId":10,"position":{"x":7100,"y":1197},"currentGold":846,"totalGold":6021,"level":11,"xp":7612,"minionsKilled":126,"jungleMinionsKilled":0,"dominionScore":0,"teamScore":0}},"events":[{"type":"ITEM_PURCHASED","timestamp":842303,"participantId":2,"itemId":3153},{"type":"ITEM_DESTROYED","timestamp":842303,"participantId":2,"itemId":3144},{"type":"ITEM_DESTROYED","timestamp":842303,"participantId":2,"itemId":1043},{"type":"WARD_PLACED","timestamp":844859,"wardType":"UNDEFINED","creatorId":1},{"type":"WARD_PLACED","timestamp":848339,"wardType":"SIGHT_WARD","creatorId":1},{"type":"WARD_PLACED","timestamp":851368,"wardType":"YELLOW_TRINKET","creatorId":9},{"type":"WARD_PLACED","timestamp":852358,"wardType":"YELLOW_TRINKET","creatorId":6},{"type":"WARD_KILL","timestamp":855361,"wardType":"CONTROL_WARD","killerId":9},{"type":"WARD_PLACED","timestamp":856384,"wardType":"UNDEFINED","creatorId":1},{"type":"WARD_PLACED","timestamp":856417,"wardType":"UNDEFINED","creatorId":6},{"type":"WARD_PLACED","timestamp":859203,"wardType":"SIGHT_WARD","creatorId":1},{"type":"CHAMPION_KILL","timestamp":863612,"position":{"x":4583,"y":7504},"killerId":5,"victimId":7,"assistingParticipantIds":[1]},{"type":"WARD_PLACED","timestamp":864404,"wardType":"UNDEFINED","creatorId":1},{"type":"WARD_PLACED","timestamp":869333,"wardType":"UNDEFINED","creatorId":6},{"type":"CHAMPION_KILL","timestamp":869662,"position":{"x":3323,"y":6233},"killerId":3,"victimId":9,"assistingParticipantIds":[1,2,4,5]},{"type":"CHAMPION_KILL","timestamp":872830,"position":{"x":4379,"y":6215},"killerId":8,"victimId":1,"assistingParticipantIds":[9,6]},{"type":"ITEM_PURCHASED","timestamp":877139,"participantId":9,"itemId":1042},{"type":"SKILL_LEVEL_UP","timestamp":877436,"participantId":10,"skillSlot":4,"levelUpType":"NORMAL"},{"type":"ITEM_PURCHASED","timestamp":877535,"participantId":9,"itemId":3006},{"type":"ITEM_DESTROYED","timestamp":877535,"participantId":9,"itemId":1001},{"type":"ITEM_DESTROYED","timestamp":877535,"participantId":9,"itemId":1042},{"type":"ITEM_PURCHASED","timestamp":878050,"participantId":9,"itemId":1042},{"type":"ITEM_PURCHASED","timestamp":881588,"participantId":7,"itemId":2303},{"type":"ITEM_DESTROYED","timestamp":881588,"participantId":7,"itemId":2049},{"type":"ITEM_DESTROYED","timestamp":881588,"participantId":7,"itemId":3097},{"type":"ITEM_PURCHASED","timestamp":882314,"participantId":1,"itemId":3401},{"type":"ITEM_DESTROYED","timestamp":882314,"participantId":1,"itemId":3097},{"type":"ITEM_DESTROYED","timestamp":882314,"participantId":1,"itemId":3067},{"type":"WARD_PLACED","timestamp":884921,"wardType":"YELLOW_TRINKET","creatorId":10},{"type":"SKILL_LEVEL_UP","timestamp":888809,"participantId":5,"skillSlot":1,"levelUpType":"NORMAL"},{"type":"ITEM_PURCHASED","timestamp":889337,"participantId":7,"itemId":2055},{"type":"WARD_PLACED","timestamp":891284,"wardType":"YELLOW_TRINKET","creatorId":3},{"type":"ITEM_PURCHASED","timestamp":892835,"participantId":4,"itemId":1011},{"type":"ITEM_DESTROYED","timestamp":893561,"participantId":8,"itemId":2003},{"type":"WARD_PLACED","timestamp":897858,"wardType":"UNDEFINED","creatorId":1},{"type":"WARD_PLACED","timestamp":897957,"wardType":"UNDEFINED","creatorId":6}],"timestamp":900441},{"participantFrames":{"1":{"participantId":1,"position":{"x":5455,"y":1159},"currentGold":469,"totalGold":3694,"level":8,"xp":4382,"minionsKilled":27,"jungleMinionsKilled":0,"dominionScore":0,"teamScore":0},"2":{"participantId":2,"position":{"x":396,"y":462},"currentGold":537,"totalGold":5587,"level":9,"xp":5960,"minionsKilled":125,"jungleMinionsKilled":0,"dominionScore":0,"teamScore":0},"3":{"participantId":3,"position":{"x":4361,"y":1119},"currentGold":352,"totalGold":4868,"level":9,"xp":6063,"minionsKilled":107,"jungleMinionsKilled":1,"dominionScore":0,"teamScore":0},"4":{"participantId":4,"position":{"x":1186,"y":1734},"currentGold":53,"totalGold":4528,"level":9,"xp":5347,"minionsKilled":9,"jungleMinionsKilled":62,"dominionScore":0,"teamScore":0},"5":{"participantId":5,"position":{"x":3134,"y":2881},"currentGold":445,"totalGold":5300,"level":10,"xp":6267,"minionsKilled":103,"jungleMinionsKilled":0,"dominionScore":0,"teamScore":0},"6":{"participantId":6,"position":{"x":10590,"y":5114},"currentGold":2978,"totalGold":8978,"level":11,"xp":7697,"minionsKilled":15,"jungleMinionsKilled":79,"dominionScore":0,"teamScore":0},"7":{"participantId":7,"position":{"x":5995,"y":6058},"currentGold":725,"totalGold":4655,"level":8,"xp":4756,"minionsKilled":19,"jungleMinionsKilled":0,"dominionScore":0,"teamScore":0},"8":{"participantId":8,"position":{"x":6267,"y":6009},"currentGold":2040,"totalGold":7115,"level":12,"xp":8987,"minionsKilled":135,"jungleMinionsKilled":0,"dominionScore":0,"teamScore":0},"9":{"participantId":9,"position":{"x":1599,"y":9915},"currentGold":899,"totalGold":6599,"level":10,"xp":6710,"minionsKilled":148,"jungleMinionsKilled":8,"dominionScore":0,"teamScore":0},"10":{"participantId":10,"position":{"x":10248,"y":4151},"currentGold":1602,"totalGold":6777,"level":11,"xp":8003,"minionsKilled":129,"jungleMinionsKilled":0,"dominionScore":0,"teamScore":0}},"events":[{"type":"ITEM_PURCHASED","timestamp":900870,"participantId":1,"itemId":2055},{"type":"BUILDING_KILL","timestamp":911189,"position":{"x":6919,"y":1483},"killerId":10,"assistingParticipantIds":[],"teamId":100,"buildingType":"TOWER_BUILDING","laneType":"BOT_LANE","towerType":"INNER_TURRET"},{"type":"CHAMPION_KILL","timestamp":915547,"position":{"x":6996,"y":5071},"killerId":6,"victimId":5,"assistingParticipantIds":[8]},{"type":"CHAMPION_KILL","timestamp":919677,"position":{"x":7121,"y":3129},"killerId":8,"victimId":3,"assistingParticipantIds":[6,10]},{"type":"WARD_PLACED","timestamp":920931,"wardType":"SIGHT_WARD","creatorId":1},{"type":"WARD_PLACED","timestamp":921493,"wardType":"UNDEFINED","creatorId":6},{"type":"WARD_PLACED","timestamp":922747,"wardType":"SIGHT_WARD","creatorId":7},{"type":"ITEM_PURCHASED","timestamp":923770,"participantId":5,"itemId":3020},{"type":"ITEM_DESTROYED","timestamp":923770,"participantId":5,"itemId":1001},{"type":"ITEM_PURCHASED","timestamp":924958,"participantId":3,"itemId":3067},{"type":"ITEM_DESTROYED","timestamp":924958,"participantId":3,"itemId":1028},{"type":"CHAMPION_KILL","timestamp":925224,"position":{"x":7460,"y":2359},"killerId":6,"victimId":4,"assistingParticipantIds":[10,7]},{"type":"SKILL_LEVEL_UP","timestamp":929917,"participantId":1,"skillSlot":1,"levelUpType":"NORMAL"},{"type":"WARD_PLACED","timestamp":930808,"wardType":"UNDEFINED","creatorId":1},{"type":"WARD_KILL","timestamp":932128,"wardType":"SIGHT_WARD","killerId":7},{"type":"SKILL_LEVEL_UP","timestamp":933172,"participantId":9,"skillSlot":1,"levelUpType":"NORMAL"},{"type":"WARD_PLACED","timestamp":935383,"wardType":"CONTROL_WARD","creatorId":7},{"type":"ITEM_DESTROYED","timestamp":935383,"participantId":7,"itemId":2055},{"type":"SKILL_LEVEL_UP","timestamp":936241,"participantId":6,"skillSlot":4,"levelUpType":"NORMAL"},{"type":"WARD_PLACED","timestamp":938247,"wardType":"SIGHT_WARD","creatorId":7},{"type":"ITEM_PURCHASED","timestamp":939140,"participantId":4,"itemId":1029},{"type":"WARD_PLACED","timestamp":939173,"wardType":"UNDEFINED","creatorId":1},{"type":"WARD_PLACED","timestamp":944039,"wardType":"YELLOW_TRINKET","creatorId":10},{"type":"WARD_PLACED","timestamp":944138,"wardType":"UNDEFINED","creatorId":6},{"type":"WARD_PLACED","timestamp":946236,"wardType":"UNDEFINED","creatorId":1},{"type":"SKILL_LEVEL_UP","timestamp":946863,"participantId":8,"skillSlot":3,"levelUpType":"NORMAL"},{"type":"BUILDING_KILL","timestamp":953161,"position":{"x":5846,"y":6396},"killerId":8,"assistingParticipantIds":[7],"teamId":100,"buildingType":"TOWER_BUILDING","laneType":"MID_LANE","towerType":"OUTER_TURRET"},{"type":"WARD_PLACED","timestamp":956465,"wardType":"UNDEFINED","creatorId":1},{"type":"ELITE_MONSTER_KILL","timestamp":958412,"position":{"x":9866,"y":4414},"killerId":6,"monsterType":"DRAGON","monsterSubType":"EARTH_DRAGON"}],"timestamp":960467},{"participantFrames":{"1":{"participantId":1,"position":{"x":2257,"y":7588},"currentGold":779,"totalGold":4004,"level":9,"xp":5056,"minionsKilled":32,"jungleMinionsKilled":0,"dominionScore":0,"teamScore":0},"2":{"participantId":2,"position":{"x":2485,"y":8147},"currentGold":408,"totalGold":5833,"level":10,"xp":6123,"minionsKilled":130,"jungleMinionsKilled":0,"dominionScore":0,"teamScore":0},"3":{"participantId":3,"position":{"x":6619,"y":892},"currentGold":868,"totalGold":5383,"level":10,"xp":6790,"minionsKilled":127,"jungleMinionsKilled":1,"dominionScore":0,"teamScore":0},"4":{"participantId":4,"position":{"x":2460,"y":6898},"currentGold":310,"totalGold":4785,"level":9,"xp":5819,"minionsKilled":10,"jungleMinionsKilled":66,"dominionScore":0,"teamScore":0},"5":{"participantId":5,"position":{"x":7898,"y":8121},"currentGold":54,"totalGold":5744,"level":10,"xp":6851,"minionsKilled":119,"jungleMinionsKilled":0,"dominionScore":0,"teamScore":0},"6":{"participantId":6,"position":{"x":6276,"y":9380},"currentGold":311,"totalGold":9511,"level":12,"xp":8629,"minionsKilled":15,"jungleMinionsKilled":95,"dominionScore":0,"teamScore":0},"7":{"participantId":7,"position":{"x":2410,"y":7471},"currentGold":176,"totalGold":5056,"level":9,"xp":5056,"minionsKilled":19,"jungleMinionsKilled":0,"dominionScore":0,"teamScore":0},"8":{"participantId":8,"position":{"x":3717,"y":7411},"currentGold":492,"totalGold":7592,"level":12,"xp":9674,"minionsKilled":138,"jungleMinionsKilled":0,"dominionScore":0,"teamScore":0},"9":{"participantId":9,"position":{"x":2469,"y":7359},"currentGold":1454,"totalGold":7154,"level":11,"xp":7701,"minionsKilled":158,"jungleMinionsKilled":12,"dominionScore":0,"teamScore":0},"10":{"participantId":10,"position":{"x":8527,"y":1214},"currentGold":668,"totalGold":7093,"level":11,"xp":8445,"minionsKilled":138,"jungleMinionsKilled":0,"dominionScore":0,"teamScore":0}},"events":[{"type":"WARD_PLACED","timestamp":962150,"wardType":"SIGHT_WARD","creatorId":7},{"type":"ITEM_PURCHASED","timestamp":962650,"participantId":10,"itemId":3052},{"type":"ITEM_DESTROYED","timestamp":962650,"participantId":10,"itemId":1036},{"type":"WARD_PLACED","timestamp":963343,"wardType":"UNDEFINED","creatorId":6},{"type":"SKILL_LEVEL_UP","timestamp":964003,"participantId":3,"skillSlot":2,"levelUpType":"NORMAL"},{"type":"ITEM_PURCHASED","timestamp":964597,"participantId":10,"itemId":1028},{"type":"WARD_PLACED","timestamp":965851,"wardType":"CONTROL_WARD","creatorId":8},{"type":"ITEM_DESTROYED","timestamp":965851,"participantId":8,"itemId":2055},{"type":"ITEM_PURCHASED","timestamp":974700,"participantId":8,"itemId":3285},{"type":"ITEM_DESTROYED","timestamp":974700,"participantId":8,"itemId":1058},{"type":"ITEM_PURCHASED","timestamp":975195,"participantId":7,"itemId":1033},{"type":"ITEM_PURCHASED","timestamp":975789,"participantId":7,"itemId":1029},{"type":"ITEM_PURCHASED","timestamp":976515,"participantId":8,"itemId":2055},{"type":"ITEM_PURCHASED","timestamp":977942,"participantId":2,"itemId":1042},{"type":"ITEM_PURCHASED","timestamp":978536,"participantId":7,"itemId":2055},{"type":"ITEM_PURCHASED","timestamp":978669,"participantId":7,"itemId":2055},{"type":"ITEM_PURCHASED","timestamp":979098,"participantId":2,"itemId":2055},{"type":"WARD_PLACED","timestamp":979701,"wardType":"YELLOW_TRINKET","creatorId":3},{"type":"WARD_PLACED","timestamp":979853,"wardType":"BLUE_TRINKET","creatorId":5},{"type":"WARD_PLACED","timestamp":980216,"wardType":"UNDEFINED","creatorId":10},{"type":"WARD_PLACED","timestamp":983079,"wardType":"UNDEFINED","creatorId":1},{"type":"WARD_KILL","timestamp":983607,"wardType":"UNDEFINED","killerId":5},{"type":"SKILL_LEVEL_UP","timestamp":989557,"participantId":9,"skillSlot":4,"levelUpType":"NORMAL"},{"type":"ITEM_PURCHASED","timestamp":991570,"participantId":6,"itemId":3100},{"type":"ITEM_DESTROYED","timestamp":991570,"participantId":6,"itemId":3057},{"type":"ITEM_SOLD","timestamp":993815,"participantId":6,"itemId":2031},{"type":"ITEM_UNDO","timestamp":996412,"participantId":6,"afterId":2031,"beforeId":0},{"type":"WARD_PLACED","timestamp":997823,"wardType":"UNDEFINED","creatorId":1},{"type":"ITEM_PURCHASED","timestamp":998284,"participantId":6,"itemId":3041},{"type":"ITEM_DESTROYED","timestamp":998284,"participantId":6,"itemId":1082},{"type":"WARD_PLACED","timestamp":1002702,"wardType":"SIGHT_WARD","creatorId":1},{"type":"WARD_PLACED","timestamp":1002841,"wardType":"BLUE_TRINKET","creatorId":2},{"type":"CHAMPION_KILL","timestamp":1004923,"position":{"x":7898,"y":8121},"killerId":8,"victimId":5,"assistingParticipantIds":[]},{"type":"WARD_PLACED","timestamp":1006507,"wardType":"YELLOW_TRINKET","creatorId":9},{"type":"ITEM_PURCHASED","timestamp":1007662,"participantId":5,"itemId":1052},{"type":"ITEM_PURCHASED","timestamp":1008289,"participantId":5,"itemId":1028},{"type":"WARD_PLACED","timestamp":1008388,"wardType":"CONTROL_WARD","creatorId":1},{"type":"ITEM_DESTROYED","timestamp":1008388,"participantId":1,"itemId":2055},{"type":"WARD_KILL","timestamp":1011506,"wardType":"YELLOW_TRINKET","killerId":4},{"type":"WARD_KILL","timestamp":1012400,"wardType":"UNDEFINED","killerId":3},{"type":"WARD_PLACED","timestamp":1012771,"wardType":"SIGHT_WARD","creatorId":7},{"type":"WARD_PLACED","timestamp":1013266,"wardType":"UNDEFINED","creatorId":6},{"type":"WARD_PLACED","timestamp":1013668,"wardType":"UNDEFINED","creatorId":1},{"type":"SKILL_LEVEL_UP","timestamp":1017194,"participantId":2,"skillSlot":1,"levelUpType":"NORMAL"},{"type":"SKILL_LEVEL_UP","timestamp":1017986,"participantId":6,"skillSlot":3,"levelUpType":"NORMAL"},{"type":"CHAMPION_KILL","timestamp":1019706,"position":{"x":2460,"y":6898},"killerId":7,"victimId":4,"assistingParticipantIds":[9]}],"timestamp":1020496},{"participantFrames":{"1":{"participantId":1,"position":{"x":5637,"y":5568},"currentGold":340,"totalGold":4190,"level":9,"xp":5110,"minionsKilled":33,"jungleMinionsKilled":0,"dominionScore":0,"teamScore":0},"2":{"participantId":2,"position":{"x":5070,"y":5218},"currentGold":251,"totalGold":5976,"level":10,"xp":6161,"minionsKilled":131,"jungleMinionsKilled":0,"dominionScore":0,"teamScore":0},"3":{"participantId":3,"position":{"x":7846,"y":1590},"currentGold":1209,"totalGold":5724,"level":11,"xp":7320,"minionsKilled":138,"jungleMinionsKilled":1,"dominionScore":0,"teamScore":0},"4":{"participantId":4,"position":{"x":7083,"y":3145},"currentGold":157,"totalGold":4932,"level":9,"xp":5819,"minionsKilled":10,"jungleMinionsKilled":66,"dominionScore":0,"teamScore":0},"5":{"participantId":5,"position":{"x":1258,"y":7623},"currentGold":313,"totalGold":6003,"level":10,"xp":7146,"minionsKilled":126,"jungleMinionsKilled":0,"dominionScore":0,"teamScore":0},"6":{"participantId":6,"position":{"x":8610,"y":4100},"currentGold":904,"totalGold":10104,"level":12,"xp":9198,"minionsKilled":20,"jungleMinionsKilled":99,"dominionScore":0,"teamScore":0},"7":{"participantId":7,"position":{"x":9733,"y":11753},"currentGold":-166,"totalGold":5564,"level":9,"xp":5487,"minionsKilled":22,"jungleMinionsKilled":0,"dominionScore":0,"teamScore":0},"8":{"participantId":8,"position":{"x":1376,"y":7987},"currentGold":1228,"totalGold":8328,"level":13,"xp":10386,"minionsKilled":141,"jungleMinionsKilled":0,"dominionScore":0,"teamScore":0},"9":{"participantId":9,"position":{"x":9584,"y":8930},"currentGold":43,"totalGold":7943,"level":11,"xp":8156,"minionsKilled":167,"jungleMinionsKilled":12,"dominionScore":0,"teamScore":0},"10":{"participantId":10,"position":{"x":7958,"y":3276},"currentGold":1124,"totalGold":7549,"level":12,"xp":8890,"minionsKilled":146,"jungleMinionsKilled":0,"dominionScore":0,"teamScore":0}},"events":[{"type":"WARD_PLACED","timestamp":1021255,"wardType":"SIGHT_WARD","creatorId":7},{"type":"SKILL_LEVEL_UP","timestamp":1022609,"participantId":7,"skillSlot":1,"levelUpType":"NORMAL"},{"type":"CHAMPION_KILL","timestamp":1024858,"position":{"x":2001,"y":7564},"killerId":9,"victimId":2,"assistingParticipantIds":[8,7]},{"type":"SKILL_LEVEL_UP","timestamp":1028491,"participantId":1,"skillSlot":3,"levelUpType":"NORMAL"},{"type":"WARD_PLACED","timestamp":1029449,"wardType":"SIGHT_WARD","creatorId":7},{"type":"WARD_PLACED","timestamp":1032536,"wardType":"YELLOW_TRINKET","creatorId":6},{"type":"WARD_PLACED","timestamp":1034326,"wardType":"UNDEFINED","creatorId":6},{"type":"WARD_KILL","timestamp":1035052,"wardType":"CONTROL_WARD","killerId":8},{"type":"WARD_KILL","timestamp":1038236,"wardType":"BLUE_TRINKET","killerId":9},{"type":"WARD_PLACED","timestamp":1039594,"wardType":"UNDEFINED","creatorId":10},{"type":"ITEM_PURCHASED","timestamp":1040664,"participantId":1,"itemId":3158},{"type":"ITEM_DESTROYED","timestamp":1040664,"participantId":1,"itemId":2422},{"type":"ITEM_PURCHASED","timestamp":1041423,"participantId":1,"itemId":3364},{"type":"ITEM_DESTROYED","timestamp":1041423,"participantId":1,"itemId":3341},{"type":"ITEM_PURCHASED","timestamp":1042149,"participantId":1,"itemId":2055},{"type":"ITEM_PURCHASED","timestamp":1044440,"participantId":4,"itemId":1029},{"type":"SKILL_LEVEL_UP","timestamp":1044638,"participantId":10,"skillSlot":2,"levelUpType":"NORMAL"},{"type":"BUILDING_KILL","timestamp":1047245,"position":{"x":1512,"y":6699},"killerId":6,"assistingParticipantIds":[9,8,7],"teamId":100,"buildingType":"TOWER_BUILDING","laneType":"TOP_LANE","towerType":"INNER_TURRET"},{"type":"ITEM_PURCHASED","timestamp":1047542,"participantId":2,"itemId":1042},{"type":"WARD_PLACED","timestamp":1049297,"wardType":"SIGHT_WARD","creatorId":7},{"type":"ITEM_PURCHASED","timestamp":1057859,"participantId":9,"itemId":3144},{"type":"ITEM_PURCHASED","timestamp":1059313,"participantId":9,"itemId":1043},{"type":"ITEM_DESTROYED","timestamp":1059313,"participantId":9,"itemId":1042},{"type":"ITEM_PURCHASED","timestamp":1060072,"participantId":9,"itemId":3363},{"type":"ITEM_DESTROYED","timestamp":1060072,"participantId":9,"itemId":3340},{"type":"ITEM_PURCHASED","timestamp":1065252,"participantId":7,"itemId":3105},{"type":"ITEM_DESTROYED","timestamp":1065252,"participantId":7,"itemId":1033},{"type":"ITEM_DESTROYED","timestamp":1065252,"participantId":7,"itemId":1029},{"type":"ITEM_PURCHASED","timestamp":1066374,"participantId":7,"itemId":1033},{"type":"ITEM_PURCHASED","timestamp":1067892,"participantId":7,"itemId":3364},{"type":"ITEM_DESTROYED","timestamp":1067892,"participantId":7,"itemId":3341},{"type":"WARD_PLACED","timestamp":1070541,"wardType":"YELLOW_TRINKET","creatorId":10},{"type":"SKILL_LEVEL_UP","timestamp":1070574,"participantId":3,"skillSlot":4,"levelUpType":"NORMAL"},{"type":"WARD_PLACED","timestamp":1070706,"wardType":"UNDEFINED","creatorId":6},{"type":"WARD_PLACED","timestamp":1073847,"wardType":"UNDEFINED","creatorId":1},{"type":"WARD_PLACED","timestamp":1074578,"wardType":"YELLOW_TRINKET","creatorId":4},{"type":"WARD_PLACED","timestamp":1076294,"wardType":"YELLOW_TRINKET","creatorId":4},{"type":"CHAMPION_KILL","timestamp":1079379,"position":{"x":1258,"y":7623},"killerId":8,"victimId":5,"assistingParticipantIds":[]}],"timestamp":1080514},{"participantFrames":{"1":{"participantId":1,"position":{"x":2162,"y":2515},"currentGold":165,"totalGold":4466,"level":9,"xp":5572,"minionsKilled":36,"jungleMinionsKilled":0,"dominionScore":0,"teamScore":0},"2":{"participantId":2,"position":{"x":1755,"y":913},"currentGold":248,"totalGold":6343,"level":10,"xp":6509,"minionsKilled":142,"jungleMinionsKilled":0,"dominionScore":0,"teamScore":0},"3":{"participantId":3,"position":{"x":2641,"y":4935},"currentGold":476,"totalGold":6091,"level":11,"xp":7914,"minionsKilled":149,"jungleMinionsKilled":1,"dominionScore":0,"teamScore":0},"4":{"participantId":4,"position":{"x":2929,"y":4469},"currentGold":307,"totalGold":5082,"level":9,"xp":5954,"minionsKilled":10,"jungleMinionsKilled":66,"dominionScore":0,"teamScore":0},"5":{"participantId":5,"position":{"x":2715,"y":4291},"currentGold":458,"totalGold":6148,"level":10,"xp":7237,"minionsKilled":127,"jungleMinionsKilled":0,"dominionScore":0,"teamScore":0},"6":{"participantId":6,"position":{"x":2981,"y":5080},"currentGold":1772,"totalGold":10972,"level":12,"xp":9866,"minionsKilled":25,"jungleMinionsKilled":99,"dominionScore":0,"teamScore":0},"7":{"participantId":7,"position":{"x":2616,"y":4550},"currentGold":291,"totalGold":6021,"level":9,"xp":5731,"minionsKilled":26,"jungleMinionsKilled":0,"dominionScore":0,"teamScore":0},"8":{"participantId":8,"position":{"x":3833,"y":5030},"currentGold":438,"totalGold":8773,"level":13,"xp":10708,"minionsKilled":149,"jungleMinionsKilled":0,"dominionScore":0,"teamScore":0},"9":{"participantId":9,"position":{"x":3579,"y":4829},"currentGold":603,"totalGold":8503,"level":12,"xp":8580,"minionsKilled":174,"jungleMinionsKilled":16,"dominionScore":0,"teamScore":0},"10":{"participantId":10,"position":{"x":5387,"y":1858},"currentGold":1881,"totalGold":8306,"level":12,"xp":9896,"minionsKilled":164,"jungleMinionsKilled":4,"dominionScore":0,"teamScore":0}},"events":[{"type":"SKILL_LEVEL_UP","timestamp":1085773,"participantId":8,"skillSlot":3,"levelUpType":"NORMAL"},{"type":"WARD_PLACED","timestamp":1085805,"wardType":"UNDEFINED","creatorId":1},{"type":"WARD_PLACED","timestamp":1091834,"wardType":"SIGHT_WARD","creatorId":1},{"type":"ITEM_PURCHASED","timestamp":1093022,"participantId":8,"itemId":3020},{"type":"ITEM_DESTROYED","timestamp":1093022,"participantId":8,"itemId":1001},{"type":"WARD_PLACED","timestamp":1093451,"wardType":"UNDEFINED","creatorId":1},{"type":"ITEM_PURCHASED","timestamp":1094243,"participantId":8,"itemId":1052},{"type":"WARD_PLACED","timestamp":1096191,"wardType":"UNDEFINED","creatorId":6},{"type":"WARD_KILL","timestamp":1096191,"wardType":"SIGHT_WARD","killerId":6},{"type":"WARD_PLACED","timestamp":1099782,"wardType":"SIGHT_WARD","creatorId":7},{"type":"CHAMPION_KILL","timestamp":1100988,"position":{"x":5331,"y":5592},"killerId":6,"victimId":2,"assistingParticipantIds":[]},{"type":"WARD_PLACED","timestamp":1101318,"wardType":"UNDEFINED","creatorId":1},{"type":"ITEM_PURCHASED","timestamp":1103705,"participantId":3,"itemId":3800},{"type":"ITEM_DESTROYED","timestamp":1103705,"participantId":3,"itemId":3024},{"type":"ITEM_DESTROYED","timestamp":1103705,"participantId":3,"itemId":3801},{"type":"WARD_PLACED","timestamp":1112427,"wardType":"UNDEFINED","creatorId":6},{"type":"WARD_PLACED","timestamp":1113549,"wardType":"YELLOW_TRINKET","creatorId":6},{"type":"WARD_PLACED","timestamp":1115678,"wardType":"CONTROL_WARD","creatorId":7},{"type":"ITEM_DESTROYED","timestamp":1115678,"participantId":7,"itemId":2055},{"type":"ITEM_SOLD","timestamp":1118339,"participantId":2,"itemId":2055},{"type":"ITEM_PURCHASED","timestamp":1119659,"participantId":2,"itemId":1051},{"type":"WARD_PLACED","timestamp":1119923,"wardType":"SIGHT_WARD","creatorId":7},{"type":"BUILDING_KILL","timestamp":1125428,"position":{"x":5048,"y":4812},"killerId":6,"assistingParticipantIds":[9,7],"teamId":100,"buildingType":"TOWER_BUILDING","laneType":"MID_LANE","towerType":"INNER_TURRET"},{"type":"ITEM_PURCHASED","timestamp":1130977,"participantId":1,"itemId":1028},{"type":"WARD_PLACED","timestamp":1131509,"wardType":"UNDEFINED","creatorId":6},{"type":"SKILL_LEVEL_UP","timestamp":1132461,"participantId":9,"skillSlot":1,"levelUpType":"NORMAL"},{"type":"WARD_PLACED","timestamp":1132593,"wardType":"UNDEFINED","creatorId":6},{"type":"ITEM_UNDO","timestamp":1132859,"participantId":1,"afterId":0,"beforeId":1028},{"type":"ITEM_PURCHASED","timestamp":1134345,"participantId":1,"itemId":1033}],"timestamp":1140533},{"participantFrames":{"1":{"participantId":1,"currentGold":280,"totalGold":4580,"level":9,"xp":5572,"minionsKilled":36,"jungleMinionsKilled":0},"2":{"participantId":2,"currentGold":310,"totalGold":6435,"level":10,"xp":6627,"minionsKilled":143,"jungleMinionsKilled":0},"3":{"participantId":3,"currentGold":36,"totalGold":6161,"level":11,"xp":7926,"minionsKilled":149,"jungleMinionsKilled":1},"4":{"participantId":4,"currentGold":392,"totalGold":5167,"level":9,"xp":5970,"minionsKilled":10,"jungleMinionsKilled":66},"5":{"participantId":5,"currentGold":508,"totalGold":6218,"level":10,"xp":7250,"minionsKilled":127,"jungleMinionsKilled":0},"6":{"participantId":6,"currentGold":2251,"totalGold":11511,"level":13,"xp":10306,"minionsKilled":25,"jungleMinionsKilled":99},"7":{"participantId":7,"currentGold":795,"totalGold":6295,"level":10,"xp":6527,"minionsKilled":27,"jungleMinionsKilled":0},"8":{"participantId":8,"currentGold":928,"totalGold":9263,"level":13,"xp":11108,"minionsKilled":153,"jungleMinionsKilled":0},"9":{"participantId":9,"currentGold":1330,"totalGold":9230,"level":12,"xp":9032,"minionsKilled":175,"jungleMinionsKilled":16},"10":{"participantId":10,"currentGold":2255,"totalGold":8680,"level":13,"xp":10454,"minionsKilled":167,"jungleMinionsKilled":4}},"events":[{"type":"WARD_PLACED","timestamp":1144363,"wardType":"UNDEFINED","creatorId":6},{"type":"WARD_PLACED","timestamp":1148011,"wardType":"UNDEFINED","creatorId":1},{"type":"WARD_PLACED","timestamp":1153791,"wardType":"CONTROL_WARD","creatorId":7},{"type":"ITEM_DESTROYED","timestamp":1153791,"participantId":7,"itemId":2055},{"type":"CHAMPION_KILL","timestamp":1154426,"position":{"x":2176,"y":5228},"killerId":9,"victimId":3,"assistingParticipantIds":[6,8]},{"type":"CHAMPION_KILL","timestamp":1155235,"position":{"x":4088,"y":1612},"killerId":10,"victimId":2,"assistingParticipantIds":[]},{"type":"WARD_PLACED","timestamp":1157395,"wardType":"UNDEFINED","creatorId":1},{"type":"SKILL_LEVEL_UP","timestamp":1157628,"participantId":10,"skillSlot":2,"levelUpType":"NORMAL"},{"type":"CHAMPION_KILL","timestamp":1158558,"position":{"x":2685,"y":4300},"killerId":8,"victimId":4,"assistingParticipantIds":[6,7]},{"type":"CHAMPION_KILL","timestamp":1159094,"position":{"x":2254,"y":3818},"killerId":6,"victimId":5,"assistingParticipantIds":[9,8,7]},{"type":"SKILL_LEVEL_UP","timestamp":1160719,"participantId":6,"skillSlot":3,"levelUpType":"NORMAL"},{"type":"SKILL_LEVEL_UP","timestamp":1161181,"participantId":7,"skillSlot":2,"levelUpType":"NORMAL"},{"type":"ITEM_PURCHASED","timestamp":1162732,"participantId":3,"itemId":1033},{"type":"CHAMPION_KILL","timestamp":1164756,"position":{"x":1586,"y":2050},"killerId":9,"victimId":1,"assistingParticipantIds":[6,8,7]},{"type":"WARD_PLACED","timestamp":1169514,"wardType":"UNDEFINED","creatorId":10}],"timestamp":1200533}],"frameInterval":60000}